vending_machine/vending_machine_def.v
// Title         : vending_machine_def.v
// Author      : Jae-Eon Jo (Jojaeeon@postech.ac.kr) 
//					Dongup Kwon (nankdu7@postech.ac.kr)

// Macro constants (prefix k & CamelCase)
`define kTotalBits 32
  
`define kItemBits 8
`define kNumItems 4

`define kCoinBits 8
`define kNumCoins 3

`define kWaitTime 10

// states 정의
`define s0 2'b00 // 대기 상태
`define s1 2'b01 // 동전 입력 상태
`define s2 2'b10 // 아이템 출력 상태
`define s3 2'b11 // 동전 반환 상태

vending_machine/change_state.v
`include "vending_machine_def.v"


module change_state(clk,reset_n,current_total_nxt,current_total);

	input clk;
	input reset_n;
	input [`kTotalBits-1:0] current_total_nxt;
	output reg [`kTotalBits-1:0] current_total;
	
	// Sequential circuit to reset or update the states
	always @(posedge clk ) begin
		if (!reset_n) begin
			// TODO: reset all states.
			current_total <= 0;
		end
		else begin
			// TODO: update all states.
			current_total <= current_total_nxt;
		end
	end
endmodule

vending_machine/calculate_current_state.v

`include "vending_machine_def.v"
	

module calculate_current_state(i_input_coin,i_select_item,item_price,coin_value,current_total,
current_total_nxt,wait_time,o_return_coin,o_available_item,o_output_item, i_trigger_return);


	input i_trigger_return;
	input [`kNumCoins-1:0] i_input_coin,o_return_coin;
	input [`kNumItems-1:0]	i_select_item;			
	input [31:0] item_price [`kNumItems-1:0];
	input [31:0] coin_value [`kNumCoins-1:0];	
	input [`kTotalBits-1:0] current_total;
	input [31:0] wait_time;
	output reg [`kNumItems-1:0] o_available_item,o_output_item;
	output reg  [`kTotalBits-1:0] current_total_nxt;
	reg [`kTotalBits-1:0] input_total, output_total, return_total;
	integer i;	
	reg [`kTotalBits-1:0] a;
	// Combinational logic for the next states
	always @(*) begin
		// TODO: current_total_nxt
		// You don't have to worry about concurrent activations in each input vector (or array).
		// Calculate the next current_total state.
		input_total = (i_input_coin[0] * coin_value[0][30:0]) + (i_input_coin[1] * coin_value[1][30:0]) + (i_input_coin[2] * coin_value[2][30:0]);
		return_total =  (o_return_coin[0] * coin_value[0][30:0]) + (o_return_coin[1] * coin_value[1][30:0]) + (o_return_coin[2] * coin_value[2][30:0]);
		a = current_total + input_total - output_total;
		if(i_trigger_return == 1 || wait_time == 0) begin
			current_total_nxt = a - return_total;
		end
		else begin
			current_total_nxt = a;
		end
	end
	
	
	// Combinational logic for the outputs
	always @(*) begin
		// TODO: o_available_item
		for (i = 0; i < `kNumItems; i = i + 1) begin
			if(item_price[i] <= current_total ) begin
				o_available_item[i] = 1'b1;
			end else begin
				o_available_item[i] = 1'b0;
			end
		end
		// TODO: o_output_item
		if(wait_time > 0) begin
			for (i = 0; i < `kNumItems; i = i + 1) begin
				if((i_select_item[i] * item_price[i] <= current_total) && (i_select_item[i] != 0)) begin
					o_output_item[i] = 1'b1;
				end else begin
					o_output_item[i] = 1'b0;
				end
			end
			output_total = (o_output_item[0] * item_price[0][30:0]) + (o_output_item[1] * item_price[1][30:0]) + (o_output_item[2] * item_price[2][30:0]) + (o_output_item[3] * item_price[3][30:0]);
		end else begin
			o_output_item = 0;
			output_total = 0;
		end
	end
 
	


endmodule

vending_machine/check_time_and_coin.v
`include "vending_machine_def.v"

	

module check_time_and_coin(i_input_coin,i_select_item,clk,reset_n,wait_time,o_return_coin, current_total);
	input clk;
	input reset_n;
	input [`kTotalBits-1:0] current_total;
	input [`kNumCoins-1:0] i_input_coin;
	input [`kNumItems-1:0]	i_select_item;
	output reg  [`kNumCoins-1:0] o_return_coin;
	output reg [31:0] wait_time;

reg [2:0] prev_i_input_coin;
reg [3:0] prev_i_select_item;

	// initiate values
	initial begin
		// TODO: initiate values
		wait_time = 0;
		o_return_coin = 0;
	end

	always @(*) begin
		// TODO: o_return_coin
		if(current_total >= 1000) begin
			o_return_coin[2] = 1'b1; //+1000원
			if (current_total >= 1500) begin
				o_return_coin[1] = 1'b1; //+ 500원
				if(current_total >= 1600) begin
					o_return_coin[0] = 1'b1; //총 1600원
				end else begin
					o_return_coin[0] = 1'b0; //총 1500원
				end
			end else begin
				o_return_coin[1] = 1'b0;
				if(current_total >= 1100) begin
					o_return_coin[0] = 1'b1; //총 1100원
				end else begin
					o_return_coin[0] = 1'b0; //총 1000원
				end
			end
		end else begin
			o_return_coin[2] =1'b0;
			if(current_total >= 500) begin
				o_return_coin[1] =1'b1;
				if(current_total >= 600) begin
					o_return_coin[0] =1'b1;
				end else begin
					o_return_coin[0] =1'b0;
				end
			end else begin
				o_return_coin[1] = 1'b0; 
				if(current_total >= 100) begin
					o_return_coin[0] =1'b1;
				end else begin
					o_return_coin[0] =1'b0;
				end
			end
		end
	end

	// update coin return time
	always @(i_input_coin, i_select_item) begin
		// TODO: update coin return time
	end

	

	always @(posedge clk ) begin
		if (!reset_n) begin
		// TODO: reset all states.
		wait_time <= 0;
		end
		else begin
		// TODO: update all states.
			if ((i_input_coin !== prev_i_input_coin) || (i_select_item !== prev_i_select_item)) begin
    		    wait_time <= 10; 
    		end else begin
    	    	if (wait_time > 0) begin
            		wait_time <= wait_time - 1;
				end
			end
    	end
    	prev_i_input_coin <= i_input_coin;
    	prev_i_select_item <= i_select_item;
	end
endmodule

vending_machine/vending_machine.v
// Title         : vending_machine.v
// Author      : Jae-Eon Jo (Jojaeeon@postech.ac.kr) 
//			     Dongup Kwon (nankdu7@postech.ac.kr) (2015.03.30)
//			     Jaehun Ryu (jaehunryu@postech.ac.kr) (2021.03.07)

`include "vending_machine_def.v"


module vending_machine (
	clk,							// Clock signal
	reset_n,						// Reset signal (active-low)

	i_input_coin,				// coin is inserted.
	i_select_item,				// item is selected.
	i_trigger_return,			// change-return is triggered 

	o_available_item,			// Sign of the item availability
	o_output_item,			// Sign of the item withdrawal
	o_return_coin				// Sign of the coin return
);

	// Ports Declaration
	// Do not modify the module interface
	input clk;
	input reset_n;
	
	input [`kNumCoins-1:0] i_input_coin;
	input [`kNumItems-1:0] i_select_item;
	input i_trigger_return;
		
	output [`kNumItems-1:0] o_available_item;
	output [`kNumItems-1:0] o_output_item;
	output [`kNumCoins-1:0] o_return_coin;


	

	// Do not modify the values.
	wire [31:0] item_price [`kNumItems-1:0];	// Price of each item
	wire [31:0] coin_value [`kNumCoins-1:0];	// Value of each coin
	assign item_price[0] = 400;
	assign item_price[1] = 500;
	assign item_price[2] = 1000;
	assign item_price[3] = 2000;
	assign coin_value[0] = 100;
	assign coin_value[1] = 500;
	assign coin_value[2] = 1000;

	// Internal states. You may add your own net variables.
	wire [`kTotalBits-1:0] current_total;
	
	// Next internal states. You may add your own net variables.
	wire [`kTotalBits-1:0] current_total_nxt;

	
	// Variables. You may add more your own net variables.
	wire [31:0] wait_time;


	// This module interface, structure, and given a number of modules are not mandatory but recommended.
	// However, Implementations that use modules are mandatory.
		
  	check_time_and_coin check_time_and_coin_module(.i_input_coin(i_input_coin),
									.current_total(current_total),
  									.i_select_item(i_select_item),
									.clk(clk),
									.reset_n(reset_n),
									.wait_time(wait_time),
									.o_return_coin(o_return_coin));

	calculate_current_state calculate_current_state_module(.i_input_coin(i_input_coin),
										.i_select_item(i_select_item),
										.item_price(item_price),
										.coin_value(coin_value),
										.current_total(current_total),
										.current_total_nxt(current_total_nxt),
										.wait_time(wait_time),
										.o_return_coin(o_return_coin),
										.o_available_item(o_available_item),
										.o_output_item(o_output_item));
	
  	change_state change_state_module(
						.clk(clk),
						.reset_n(reset_n),
						.current_total_nxt(current_total_nxt),
						.current_total(current_total));

	always @(*) begin
		
		if(i_trigger_return) begin
			
		end
	end

endmodule

vending_machine/waveform.vcd
$version Generated by VerilatedVcd $end
$timescale 1ps $end
 $scope module TOP $end
  $var wire 1 4 clk $end
  $var wire 1 5 reset_n $end
  $var wire 3 6 i_input_coin [2:0] $end
  $var wire 4 7 i_select_item [3:0] $end
  $var wire 1 8 i_trigger_return $end
  $var wire 4 9 o_available_item [3:0] $end
  $var wire 4 : o_output_item [3:0] $end
  $var wire 3 ; o_return_coin [2:0] $end
  $scope module vending_machine $end
   $var wire 1 4 clk $end
   $var wire 1 5 reset_n $end
   $var wire 3 6 i_input_coin [2:0] $end
   $var wire 4 7 i_select_item [3:0] $end
   $var wire 1 8 i_trigger_return $end
   $var wire 4 9 o_available_item [3:0] $end
   $var wire 4 : o_output_item [3:0] $end
   $var wire 3 ; o_return_coin [2:0] $end
   $var wire 32 # item_price[0] [31:0] $end
   $var wire 32 $ item_price[1] [31:0] $end
   $var wire 32 % item_price[2] [31:0] $end
   $var wire 32 & item_price[3] [31:0] $end
   $var wire 32 ' coin_value[0] [31:0] $end
   $var wire 32 ( coin_value[1] [31:0] $end
   $var wire 32 ) coin_value[2] [31:0] $end
   $var wire 32 / current_total [31:0] $end
   $var wire 32 * current_total_nxt [31:0] $end
   $var wire 32 0 wait_time [31:0] $end
   $scope module calculate_current_state_module $end
    $var wire 1 8 i_trigger_return $end
    $var wire 3 6 i_input_coin [2:0] $end
    $var wire 3 ; o_return_coin [2:0] $end
    $var wire 4 7 i_select_item [3:0] $end
    $var wire 32 # item_price[0] [31:0] $end
    $var wire 32 $ item_price[1] [31:0] $end
    $var wire 32 % item_price[2] [31:0] $end
    $var wire 32 & item_price[3] [31:0] $end
    $var wire 32 ' coin_value[0] [31:0] $end
    $var wire 32 ( coin_value[1] [31:0] $end
    $var wire 32 ) coin_value[2] [31:0] $end
    $var wire 32 / current_total [31:0] $end
    $var wire 32 0 wait_time [31:0] $end
    $var wire 4 9 o_available_item [3:0] $end
    $var wire 4 : o_output_item [3:0] $end
    $var wire 32 * current_total_nxt [31:0] $end
    $var wire 32 + input_total [31:0] $end
    $var wire 32 , output_total [31:0] $end
    $var wire 32 - return_total [31:0] $end
    $var wire 32 1 i [31:0] $end
    $var wire 32 . a [31:0] $end
   $upscope $end
   $scope module change_state_module $end
    $var wire 1 4 clk $end
    $var wire 1 5 reset_n $end
    $var wire 32 * current_total_nxt [31:0] $end
    $var wire 32 / current_total [31:0] $end
   $upscope $end
   $scope module check_time_and_coin_module $end
    $var wire 1 4 clk $end
    $var wire 1 5 reset_n $end
    $var wire 32 / current_total [31:0] $end
    $var wire 3 6 i_input_coin [2:0] $end
    $var wire 4 7 i_select_item [3:0] $end
    $var wire 3 ; o_return_coin [2:0] $end
    $var wire 32 0 wait_time [31:0] $end
    $var wire 3 2 prev_i_input_coin [2:0] $end
    $var wire 4 3 prev_i_select_item [3:0] $end
   $upscope $end
  $upscope $end
 $upscope $end
$enddefinitions $end


#0
b00000000000000000000000110010000 #
b00000000000000000000000111110100 $
b00000000000000000000001111101000 %
b00000000000000000000011111010000 &
b00000000000000000000000001100100 '
b00000000000000000000000111110100 (
b00000000000000000000001111101000 )
b11000110010101111110100010101001 *
b00000000000000000000000000000000 +
b00000000000000000000000000000000 ,
b00000000000000000000011001000000 -
b11000110010101111110111011101001 .
b11000110010101111110111011101001 /
b00000000000000000000000000000000 0
b00000000000000000000000000000100 1
b010 2
b1000 3
14
15
b000 6
b0000 7
08
b1111 9
b0000 :
b111 ;
#1
04
#2
b00000000000000000000000000000000 *
b00000000000000000000000000000000 -
b00000000000000000000000000000000 .
b00000000000000000000000000000000 /
b000 2
b0000 3
14
05
b0000 9
b000 ;
#3
04
#4
14
#5
04
#6
14
15
#7
04
#8
b00000000000000000000000011001000 *
b00000000000000000000000001100100 +
b00000000000000000000000001100100 -
b00000000000000000000000011001000 .
b00000000000000000000000001100100 /
b00000000000000000000000000001010 0
b001 2
14
b001 6
b001 ;
#9
04
#10
b00000000000000000000000001100100 *
b00000000000000000000000000000000 +
b00000000000000000000000001100100 .
b000 2
14
b000 6
#11
04
#12
b00000000000000000000000100101100 *
b00000000000000000000000001100100 +
b00000000000000000000000100101100 .
b00000000000000000000000011001000 /
b001 2
14
b001 6
#13
04
#14
b00000000000000000000000011001000 *
b00000000000000000000000000000000 +
b00000000000000000000000011001000 .
b000 2
14
b000 6
#15
04
#16
b00000000000000000000000110010000 *
b00000000000000000000000001100100 +
b00000000000000000000000110010000 .
b00000000000000000000000100101100 /
b001 2
14
b001 6
#17
04
#18
b00000000000000000000000100101100 *
b00000000000000000000000000000000 +
b00000000000000000000000100101100 .
b000 2
14
b000 6
#19
04
#20
b00000000000000000000000111110100 *
b00000000000000000000000001100100 +
b00000000000000000000000111110100 .
b00000000000000000000000110010000 /
b001 2
14
b001 6
b0001 9
#21
04
#22
b00000000000000000000000110010000 *
b00000000000000000000000000000000 +
b00000000000000000000000110010000 .
b000 2
14
b000 6
#23
04
#24
b00000000000000000000001001011000 *
b00000000000000000000000001100100 +
b00000000000000000000000111110100 -
b00000000000000000000001001011000 .
b00000000000000000000000111110100 /
b001 2
14
b001 6
b0011 9
b010 ;
#25
04
#26
b00000000000000000000000111110100 *
b00000000000000000000000000000000 +
b00000000000000000000000111110100 .
b000 2
14
b000 6
#27
04
#28
b00000000000000000000000000001001 0
14
#29
04
#30
b00000000000000000000000000000000 *
b00000000000000000000000000000000 -
b00000000000000000000000000000000 .
b00000000000000000000000000000000 /
b00000000000000000000000000000000 0
14
05
b0000 9
b000 ;
#31
04
#32
14
#33
04
#34
14
15
#35
04
#36
b00000000000000000000001111101000 *
b00000000000000000000000111110100 +
b00000000000000000000000111110100 -
b00000000000000000000001111101000 .
b00000000000000000000000111110100 /
b00000000000000000000000000001010 0
b010 2
14
b010 6
b0011 9
b010 ;
#37
04
#38
b00000000000000000000000111110100 *
b00000000000000000000000000000000 +
b00000000000000000000000111110100 .
b000 2
14
b000 6
#39
04
#40
b00000000000000000000010111011100 *
b00000000000000000000000111110100 +
b00000000000000000000001111101000 -
b00000000000000000000010111011100 .
b00000000000000000000001111101000 /
b010 2
14
b010 6
b0111 9
b100 ;
#41
04
#42
b00000000000000000000001111101000 *
b00000000000000000000000000000000 +
b00000000000000000000001111101000 .
b000 2
14
b000 6
#43
04
#44
b00000000000000000000011111010000 *
b00000000000000000000000111110100 +
b00000000000000000000010111011100 -
b00000000000000000000011111010000 .
b00000000000000000000010111011100 /
b010 2
14
b010 6
b110 ;
#45
04
#46
b00000000000000000000010111011100 *
b00000000000000000000000000000000 +
b00000000000000000000010111011100 .
b000 2
14
b000 6
#47
04
#48
b00000000000000000000100111000100 *
b00000000000000000000000111110100 +
b00000000000000000000011001000000 -
b00000000000000000000100111000100 .
b00000000000000000000011111010000 /
b010 2
14
b010 6
b1111 9
b111 ;
#49
04
#50
b00000000000000000000011111010000 *
b00000000000000000000000000000000 +
b00000000000000000000011111010000 .
b000 2
14
b000 6
#51
04
#52
b00000000000000000000000000001001 0
14
#53
04
#54
b00000000000000000000000000000000 *
b00000000000000000000000000000000 -
b00000000000000000000000000000000 .
b00000000000000000000000000000000 /
b00000000000000000000000000000000 0
14
05
b0000 9
b000 ;
#55
04
#56
14
#57
04
#58
14
15
#59
04
#60
b00000000000000000000011111010000 *
b00000000000000000000001111101000 +
b00000000000000000000001111101000 -
b00000000000000000000011111010000 .
b00000000000000000000001111101000 /
b00000000000000000000000000001010 0
b100 2
14
b100 6
b0111 9
b100 ;
#61
04
#62
b00000000000000000000001111101000 *
b00000000000000000000000000000000 +
b00000000000000000000001111101000 .
b000 2
14
b000 6
#63
04
#64
b00000000000000000000101110111000 *
b00000000000000000000001111101000 +
b00000000000000000000011001000000 -
b00000000000000000000101110111000 .
b00000000000000000000011111010000 /
b100 2
14
b100 6
b1111 9
b111 ;
#65
04
#66
b00000000000000000000011111010000 *
b00000000000000000000000000000000 +
b00000000000000000000011111010000 .
b000 2
14
b000 6
#67
04
#68
b00000000000000000000000000001001 0
14
#69
04
#70
b00000000000000000000000000000000 *
b00000000000000000000000000000000 -
b00000000000000000000000000000000 .
b00000000000000000000000000000000 /
b00000000000000000000000000000000 0
14
05
b0000 9
b000 ;
#71
04
#72
14
#73
04
#74
14
15
#75
04
#76
b00000000000000000000011111010000 *
b00000000000000000000001111101000 +
b00000000000000000000001111101000 -
b00000000000000000000011111010000 .
b00000000000000000000001111101000 /
b00000000000000000000000000001010 0
b100 2
14
b100 6
b0111 9
b100 ;
#77
04
#78
b00000000000000000000001111101000 *
b00000000000000000000000000000000 +
b00000000000000000000001111101000 .
b000 2
14
b000 6
#79
04
#80
b00000000000000000000101110111000 *
b00000000000000000000001111101000 +
b00000000000000000000011001000000 -
b00000000000000000000101110111000 .
b00000000000000000000011111010000 /
b100 2
14
b100 6
b1111 9
b111 ;
#81
04
#82
b00000000000000000000011111010000 *
b00000000000000000000000000000000 +
b00000000000000000000011111010000 .
b000 2
14
b000 6
#83
04
#84
b00000000000000000000111110100000 *
b00000000000000000000001111101000 +
b00000000000000000000111110100000 .
b00000000000000000000101110111000 /
b100 2
14
b100 6
#85
04
#86
b00000000000000000000101110111000 *
b00000000000000000000000000000000 +
b00000000000000000000101110111000 .
b000 2
14
b000 6
#87
04
#88
b00000000000000000000100010011000 *
b00000000000000000000000110010000 ,
b00000000000000000000100010011000 .
b00000000000000000000101000101000 /
b0001 3
14
b0001 7
b0001 :
#89
04
#90
b00000000000000000000101000101000 *
b00000000000000000000000000000000 ,
b00000000000000000000101000101000 .
b0000 3
14
b0000 7
b0000 :
#91
04
#92
b00000000000000000000000000001001 0
14
#93
04
#94
b00000000000000000000000000001000 0
14
#95
04
#96
b00000000000000000000011100001000 *
b00000000000000000000000110010000 ,
b00000000000000000000011100001000 .
b00000000000000000000100010011000 /
b00000000000000000000000000001010 0
b0001 3
14
b0001 7
b0001 :
#97
04
#98
b00000000000000000000100010011000 *
b00000000000000000000000000000000 ,
b00000000000000000000100010011000 .
b0000 3
14
b0000 7
b0000 :
#99
04
#100
b00000000000000000000000000001001 0
14
#101
04
#102
b00000000000000000000000000001000 0
14
#103
04
#104
b00000000000000000000010101111000 *
b00000000000000000000000110010000 ,
b00000000000000000000010101111000 .
b00000000000000000000011100001000 /
b00000000000000000000000000001010 0
b0001 3
14
b0001 7
b0111 9
b0001 :
#105
04
#106
b00000000000000000000011100001000 *
b00000000000000000000000000000000 ,
b00000000000000000000011100001000 .
b0000 3
14
b0000 7
b0000 :
#107
04
#108
b00000000000000000000000000001001 0
14
#109
04
#110
b00000000000000000000000000001000 0
14
#111
04
#112
b00000000000000000000001111101000 *
b00000000000000000000000110010000 ,
b00000000000000000000010001001100 -
b00000000000000000000001111101000 .
b00000000000000000000010101111000 /
b00000000000000000000000000001010 0
b0001 3
14
b0001 7
b0001 :
b101 ;
#113
04
#114
b00000000000000000000010101111000 *
b00000000000000000000000000000000 ,
b00000000000000000000010101111000 .
b0000 3
14
b0000 7
b0000 :
#115
04
#116
b00000000000000000000000000001001 0
14
#117
04
#118
b00000000000000000000000000001000 0
14
#119
04
#120
b00000000000000000000001001011000 *
b00000000000000000000000110010000 ,
b00000000000000000000001111101000 -
b00000000000000000000001001011000 .
b00000000000000000000001111101000 /
b00000000000000000000000000001010 0
b0001 3
14
b0001 7
b0001 :
b100 ;
#121
04
#122
b00000000000000000000001111101000 *
b00000000000000000000000000000000 ,
b00000000000000000000001111101000 .
b0000 3
14
b0000 7
b0000 :
#123
04
#124
b00000000000000000000000000001001 0
14
#125
04
#126
b00000000000000000000000000001000 0
14
#127
04
#128
b00000000000000000000000011001000 *
b00000000000000000000000110010000 ,
b00000000000000000000001001011000 -
b00000000000000000000000011001000 .
b00000000000000000000001001011000 /
b00000000000000000000000000001010 0
b0001 3
14
b0001 7
b0011 9
b0001 :
b011 ;
#129
04
#130
b00000000000000000000001001011000 *
b00000000000000000000000000000000 ,
b00000000000000000000001001011000 .
b0000 3
14
b0000 7
b0000 :
#131
04
#132
b00000000000000000000000000001001 0
14
#133
04
#134
b00000000000000000000000000001000 0
14
#135
04
#136
b00000000000000000000000011001000 *
b00000000000000000000000001100100 -
b00000000000000000000000011001000 .
b00000000000000000000000011001000 /
b00000000000000000000000000001010 0
b0001 3
14
b0001 7
b0000 9
b001 ;
#137
04
#138
b0000 3
14
b0000 7
#139
04
#140
b00000000000000000000000000001001 0
14
#141
04
#142
b00000000000000000000000000001000 0
14
#143
04
#144
b00000000000000000000000000000111 0
14
#145
04
#146
b00000000000000000000000000000110 0
14
#147
04
#148
b00000000000000000000100010011000 *
b00000000000000000000001111101000 +
b00000000000000000000010001001100 -
b00000000000000000000100010011000 .
b00000000000000000000010010110000 /
b00000000000000000000000000001010 0
b100 2
14
b100 6
b0111 9
b101 ;
#149
04
#150
b00000000000000000000010010110000 *
b00000000000000000000000000000000 +
b00000000000000000000010010110000 .
b000 2
14
b000 6
#151
04
#152
b00000000000000000000110010000000 *
b00000000000000000000001111101000 +
b00000000000000000000011001000000 -
b00000000000000000000110010000000 .
b00000000000000000000100010011000 /
b100 2
14
b100 6
b1111 9
b111 ;
#153
04
#154
b00000000000000000000100010011000 *
b00000000000000000000000000000000 +
b00000000000000000000100010011000 .
b000 2
14
b000 6
#155
04
#156
b00000000000000000001000001101000 *
b00000000000000000000001111101000 +
b00000000000000000001000001101000 .
b00000000000000000000110010000000 /
b100 2
14
b100 6
#157
04
#158
b00000000000000000000110010000000 *
b00000000000000000000000000000000 +
b00000000000000000000110010000000 .
b000 2
14
b000 6
#159
04
#160
b00000000000000000000100010011000 *
b00000000000000000000000111110100 ,
b00000000000000000000100010011000 .
b00000000000000000000101010001100 /
b0010 3
14
b0010 7
b0010 :
#161
04
#162
b00000000000000000000101010001100 *
b00000000000000000000000000000000 ,
b00000000000000000000101010001100 .
b0000 3
14
b0000 7
b0000 :
#163
04
#164
b00000000000000000000000000001001 0
14
#165
04
#166
b00000000000000000000000000001000 0
14
#167
04
#168
b00000000000000000000011010100100 *
b00000000000000000000000111110100 ,
b00000000000000000000011010100100 .
b00000000000000000000100010011000 /
b00000000000000000000000000001010 0
b0010 3
14
b0010 7
b0010 :
#169
04
#170
b00000000000000000000100010011000 *
b00000000000000000000000000000000 ,
b00000000000000000000100010011000 .
b0000 3
14
b0000 7
b0000 :
#171
04
#172
b00000000000000000000000000001001 0
14
#173
04
#174
b00000000000000000000000000001000 0
14
#175
04
#176
b00000000000000000000010010110000 *
b00000000000000000000000111110100 ,
b00000000000000000000010010110000 .
b00000000000000000000011010100100 /
b00000000000000000000000000001010 0
b0010 3
14
b0010 7
b0111 9
b0010 :
#177
04
#178
b00000000000000000000011010100100 *
b00000000000000000000000000000000 ,
b00000000000000000000011010100100 .
b0000 3
14
b0000 7
b0000 :
#179
04
#180
b00000000000000000000000000001001 0
14
#181
04
#182
b00000000000000000000000000001000 0
14
#183
04
#184
b00000000000000000000001010111100 *
b00000000000000000000000111110100 ,
b00000000000000000000010001001100 -
b00000000000000000000001010111100 .
b00000000000000000000010010110000 /
b00000000000000000000000000001010 0
b0010 3
14
b0010 7
b0010 :
b101 ;
#185
04
#186
b00000000000000000000010010110000 *
b00000000000000000000000000000000 ,
b00000000000000000000010010110000 .
b0000 3
14
b0000 7
b0000 :
#187
04
#188
b00000000000000000000000000001001 0
14
#189
04
#190
b00000000000000000000000000001000 0
14
#191
04
#192
b00000000000000000000000011001000 *
b00000000000000000000000111110100 ,
b00000000000000000000001001011000 -
b00000000000000000000000011001000 .
b00000000000000000000001010111100 /
b00000000000000000000000000001010 0
b0010 3
14
b0010 7
b0011 9
b0010 :
b011 ;
#193
04
#194
b00000000000000000000001010111100 *
b00000000000000000000000000000000 ,
b00000000000000000000001010111100 .
b0000 3
14
b0000 7
b0000 :
#195
04
#196
b00000000000000000000000000001001 0
14
#197
04
#198
b00000000000000000000000000001000 0
14
#199
04
#200
b00000000000000000000000011001000 *
b00000000000000000000000001100100 -
b00000000000000000000000011001000 .
b00000000000000000000000011001000 /
b00000000000000000000000000001010 0
b0010 3
14
b0010 7
b0000 9
b001 ;
#201
04
#202
b0000 3
14
b0000 7
#203
04
#204
b00000000000000000000000000001001 0
14
#205
04
#206
b00000000000000000000000000001000 0
14
#207
04
#208
b00000000000000000000000110010000 *
b00000000000000000000000001100100 +
b00000000000000000000000110010000 .
b00000000000000000000000100101100 /
b00000000000000000000000000001010 0
b001 2
14
b001 6
#209
04
#210
b00000000000000000000000100101100 *
b00000000000000000000000000000000 +
b00000000000000000000000100101100 .
b000 2
14
b000 6
#211
04
#212
b00000000000000000000000111110100 *
b00000000000000000000000001100100 +
b00000000000000000000000111110100 .
b00000000000000000000000110010000 /
b001 2
14
b001 6
b0001 9
#213
04
#214
b00000000000000000000000110010000 *
b00000000000000000000000000000000 +
b00000000000000000000000110010000 .
b000 2
14
b000 6
#215
04
#216
b00000000000000000000100101100000 *
b00000000000000000000001111101000 +
b00000000000000000000010001001100 -
b00000000000000000000100101100000 .
b00000000000000000000010101111000 /
b100 2
14
b100 6
b0111 9
b101 ;
#217
04
#218
b00000000000000000000010101111000 *
b00000000000000000000000000000000 +
b00000000000000000000010101111000 .
b000 2
14
b000 6
#219
04
#220
b00000000000000000000110101001000 *
b00000000000000000000001111101000 +
b00000000000000000000011001000000 -
b00000000000000000000110101001000 .
b00000000000000000000100101100000 /
b100 2
14
b100 6
b1111 9
b111 ;
#221
04
#222
b00000000000000000000100101100000 *
b00000000000000000000000000000000 +
b00000000000000000000100101100000 .
b000 2
14
b000 6
#223
04
#224
b00000000000000000001000100110000 *
b00000000000000000000001111101000 +
b00000000000000000001000100110000 .
b00000000000000000000110101001000 /
b100 2
14
b100 6
#225
04
#226
b00000000000000000000110101001000 *
b00000000000000000000000000000000 +
b00000000000000000000110101001000 .
b000 2
14
b000 6
#227
04
#228
b00000000000000000000010101111000 *
b00000000000000000000001111101000 ,
b00000000000000000000010101111000 .
b00000000000000000000100101100000 /
b0100 3
14
b0100 7
b0100 :
#229
04
#230
b00000000000000000000100101100000 *
b00000000000000000000000000000000 ,
b00000000000000000000100101100000 .
b0000 3
14
b0000 7
b0000 :
#231
04
#232
b00000000000000000000000000001001 0
14
#233
04
#234
b00000000000000000000000000001000 0
14
#235
04
#236
b00000000000000000000000110010000 *
b00000000000000000000001111101000 ,
b00000000000000000000010001001100 -
b00000000000000000000000110010000 .
b00000000000000000000010101111000 /
b00000000000000000000000000001010 0
b0100 3
14
b0100 7
b0111 9
b0100 :
b101 ;
#237
04
#238
b00000000000000000000010101111000 *
b00000000000000000000000000000000 ,
b00000000000000000000010101111000 .
b0000 3
14
b0000 7
b0000 :
#239
04
#240
b00000000000000000000000000001001 0
14
#241
04
#242
b00000000000000000000000000001000 0
14
#243
04
#244
b00000000000000000000000110010000 *
b00000000000000000000000001100100 -
b00000000000000000000000110010000 .
b00000000000000000000000110010000 /
b00000000000000000000000000001010 0
b0100 3
14
b0100 7
b0001 9
b001 ;
#245
04
#246
b0000 3
14
b0000 7
#247
04
#248
b00000000000000000000000000001001 0
14
#249
04
#250
b00000000000000000000000000001000 0
14
#251
04
#252
b00000000000000000000100101100000 *
b00000000000000000000001111101000 +
b00000000000000000000010001001100 -
b00000000000000000000100101100000 .
b00000000000000000000010101111000 /
b00000000000000000000000000001010 0
b100 2
14
b100 6
b0111 9
b101 ;
#253
04
#254
b00000000000000000000010101111000 *
b00000000000000000000000000000000 +
b00000000000000000000010101111000 .
b000 2
14
b000 6
#255
04
#256
b00000000000000000000110101001000 *
b00000000000000000000001111101000 +
b00000000000000000000011001000000 -
b00000000000000000000110101001000 .
b00000000000000000000100101100000 /
b100 2
14
b100 6
b1111 9
b111 ;
#257
04
#258
b00000000000000000000100101100000 *
b00000000000000000000000000000000 +
b00000000000000000000100101100000 .
b000 2
14
b000 6
#259
04
#260
b00000000000000000001000100110000 *
b00000000000000000000001111101000 +
b00000000000000000001000100110000 .
b00000000000000000000110101001000 /
b100 2
14
b100 6
#261
04
#262
b00000000000000000000110101001000 *
b00000000000000000000000000000000 +
b00000000000000000000110101001000 .
b000 2
14
b000 6
#263
04
#264
b00000000000000000000010101111000 *
b00000000000000000000010001001100 -
b00000000000000000000010101111000 .
b00000000000000000000010101111000 /
b1000 3
14
b1000 7
b0111 9
b101 ;
#265
04
#266
b0000 3
14
b0000 7
#267
04
#268
b00000000000000000000000000001001 0
14
#269
04
#270
b00000000000000000000000000001000 0
14
#271
04
#272
b00000000000000000000110101001000 *
b00000000000000000000001111101000 +
b00000000000000000000011001000000 -
b00000000000000000000110101001000 .
b00000000000000000000100101100000 /
b00000000000000000000000000001010 0
b100 2
14
b100 6
b1111 9
b111 ;
#273
04
#274
b00000000000000000000100101100000 *
b00000000000000000000000000000000 +
b00000000000000000000100101100000 .
b000 2
14
b000 6
#275
04
#276
b00000000000000000000000110010000 *
b00000000000000000000000001100100 -
b00000000000000000000000110010000 .
b00000000000000000000000110010000 /
b1000 3
14
b1000 7
b0001 9
b001 ;
#277
04
#278
b0000 3
14
b0000 7
#279
04
#280
b00000000000000000000000000001001 0
14
#281
04
#282
b00000000000000000000000000001000 0
14
#283
04
#284
b00000000000000000000001001011000 *
b00000000000000000000000001100100 +
b00000000000000000000000111110100 -
b00000000000000000000001001011000 .
b00000000000000000000000111110100 /
b00000000000000000000000000001010 0
b001 2
14
b001 6
b0011 9
b010 ;
#285
04
#286
b00000000000000000000000111110100 *
b00000000000000000000000000000000 +
b00000000000000000000000111110100 .
b000 2
14
b000 6
#287
04
#288
b00000000000000000000001010111100 *
b00000000000000000000000001100100 +
b00000000000000000000001001011000 -
b00000000000000000000001010111100 .
b00000000000000000000001001011000 /
b001 2
14
b001 6
b011 ;
#289
04
#290
b00000000000000000000001001011000 *
b00000000000000000000000000000000 +
b00000000000000000000001001011000 .
b000 2
14
b000 6
#291
04
#292
b00000000000000000000001100100000 *
b00000000000000000000000001100100 +
b00000000000000000000001100100000 .
b00000000000000000000001010111100 /
b001 2
14
b001 6
#293
04
#294
b00000000000000000000001010111100 *
b00000000000000000000000000000000 +
b00000000000000000000001010111100 .
b000 2
14
b000 6
#295
04
