vending_machine/vending_machine_def.v
// Title         : vending_machine_def.v
// Author      : Jae-Eon Jo (Jojaeeon@postech.ac.kr) 
//					Dongup Kwon (nankdu7@postech.ac.kr)

// Macro constants (prefix k & CamelCase)
`define kTotalBits 32
  
`define kItemBits 8
`define kNumItems 4

`define kCoinBits 8
`define kNumCoins 3

`define kWaitTime 10

// states 정의
`define s0 2'b00 // 대기 상태
`define s1 2'b01 // 동전 입력 상태
`define s2 2'b10 // 아이템 출력 상태
`define s3 2'b11 // 동전 반환 상태

vending_machine/change_state.v
`include "vending_machine_def.v"


module change_state(clk,reset_n,current_total_nxt,current_total);

	input clk;
	input reset_n;
	input [`kTotalBits-1:0] current_total_nxt;
	output reg [`kTotalBits-1:0] current_total;
	
	// Sequential circuit to reset or update the states
	always @(posedge clk ) begin
		if (!reset_n) begin
			// TODO: reset all states.
			current_total <= 0;
		end
		else begin
			// TODO: update all states.
			current_total <= current_total_nxt;
		end
	end
endmodule

vending_machine/calculate_current_state.v

`include "vending_machine_def.v"
	

module calculate_current_state(i_input_coin,i_select_item,item_price,coin_value,current_total,
current_total_nxt,wait_time,o_return_coin,o_available_item,o_output_item, return_total);


	input [`kNumCoins-1:0] i_input_coin,o_return_coin;
	input [`kNumItems-1:0]	i_select_item;			
	input [31:0] item_price [`kNumItems-1:0];
	input [31:0] coin_value [`kNumCoins-1:0];	
	input [`kTotalBits-1:0] current_total;
	input [31:0] wait_time;
	output reg [`kNumItems-1:0] o_available_item,o_output_item;
	output reg  [`kTotalBits-1:0] current_total_nxt, return_total;
	reg [`kTotalBits-1:0] input_total, output_total;
	integer i;	
	reg [`kTotalBits-1:0] a;
	// Combinational logic for the next states
	always @(*) begin
		// TODO: current_total_nxt
		// You don't have to worry about concurrent activations in each input vector (or array).
		// Calculate the next current_total state.
		input_total = (i_input_coin[0] * coin_value[0][30:0]) + (i_input_coin[1] * coin_value[1][30:0]) + (i_input_coin[2] * coin_value[2][30:0]);
		return_total =  (o_return_coin[0] * coin_value[0][30:0]) + (o_return_coin[1] * coin_value[1][30:0]) + (o_return_coin[2] * coin_value[2][30:0]);
		a = current_total + input_total - output_total;
		if(wait_time == 0) begin
			current_total_nxt = a - return_total;
		end
		else begin
			current_total_nxt = a;
		end
	end
	
	
	// Combinational logic for the outputs
	always @(*) begin
		// TODO: o_available_item
		for (i = 0; i < `kNumItems; i = i + 1) begin
			if(item_price[i] <= current_total ) begin
				o_available_item[i] = 1'b1;
			end else begin
				o_available_item[i] = 1'b0;
			end
		end
		// TODO: o_output_item
		if(wait_time > 0) begin
			for (i = 0; i < `kNumItems; i = i + 1) begin
				if((i_select_item[i] * item_price[i] <= current_total) && (i_select_item[i] != 0)) begin
					o_output_item[i] = 1'b1;
				end else begin
					o_output_item[i] = 1'b0;
				end
			end
			output_total = (o_output_item[0] * item_price[0][30:0]) + (o_output_item[1] * item_price[1][30:0]) + (o_output_item[2] * item_price[2][30:0]) + (o_output_item[3] * item_price[3][30:0]);
		end else begin
			o_output_item = 0;
			output_total = 0;
		end
	end
 
	


endmodule

vending_machine/check_time_and_coin.v
`include "vending_machine_def.v"

	

module check_time_and_coin(i_input_coin,i_select_item,clk,reset_n,wait_time,o_return_coin, current_total);
	input clk;
	input reset_n;
	input [`kTotalBits-1:0] current_total;
	input [`kNumCoins-1:0] i_input_coin;
	input [`kNumItems-1:0]	i_select_item;
	output reg  [`kNumCoins-1:0] o_return_coin;
	output reg [31:0] wait_time;

reg [2:0] prev_i_input_coin;
reg [3:0] prev_i_select_item;

	// initiate values
	initial begin
		// TODO: initiate values
		wait_time = 0;
		o_return_coin = 0;
	end

	always @(*) begin
		// TODO: o_return_coin
		if(current_total >= 1000) begin
			o_return_coin[2] = 1'b1; //+1000원
			if (current_total >= 1500) begin
				o_return_coin[1] = 1'b1; //+ 500원
				if(current_total >= 1600) begin
					o_return_coin[0] = 1'b1; //총 1600원
				end else begin
					o_return_coin[0] = 1'b0; //총 1500원
				end
			end else begin
				o_return_coin[1] = 1'b0;
				if(current_total >= 1100) begin
					o_return_coin[0] = 1'b1; //총 1100원
				end else begin
					o_return_coin[0] = 1'b0; //총 1000원
				end
			end
		end else begin
			o_return_coin[2] =1'b0;
			if(current_total >= 500) begin
				o_return_coin[1] =1'b1;
				if(current_total >= 600) begin
					o_return_coin[0] =1'b1;
				end else begin
					o_return_coin[0] =1'b0;
				end
			end else begin
				o_return_coin[1] = 1'b0; 
				if(current_total >= 100) begin
					o_return_coin[0] =1'b1;
				end else begin
					o_return_coin[0] =1'b0;
				end
			end
		end
	end

	// update coin return time
	always @(i_input_coin, i_select_item) begin
		// TODO: update coin return time
	end

	

	always @(posedge clk ) begin
		if (!reset_n) begin
		// TODO: reset all states.
		wait_time <= 0;
		end
		else begin
		// TODO: update all states.
			if ((i_input_coin !== prev_i_input_coin) || (i_select_item !== prev_i_select_item)) begin
    		    wait_time <= 10; 
    		end else begin
    	    	if (wait_time > 0) begin
            		wait_time <= wait_time - 1;
				end
			end
    	end
    	prev_i_input_coin <= i_input_coin;
    	prev_i_select_item <= i_select_item;
	end
endmodule

vending_machine/vending_machine.v
// Title         : vending_machine.v
// Author      : Jae-Eon Jo (Jojaeeon@postech.ac.kr) 
//			     Dongup Kwon (nankdu7@postech.ac.kr) (2015.03.30)
//			     Jaehun Ryu (jaehunryu@postech.ac.kr) (2021.03.07)

`include "vending_machine_def.v"


module vending_machine (
	clk,							// Clock signal
	reset_n,						// Reset signal (active-low)

	i_input_coin,				// coin is inserted.
	i_select_item,				// item is selected.
	i_trigger_return,			// change-return is triggered 

	o_available_item,			// Sign of the item availability
	o_output_item,			// Sign of the item withdrawal
	o_return_coin				// Sign of the coin return
);

	// Ports Declaration
	// Do not modify the module interface
	input clk;
	input reset_n;
	
	input [`kNumCoins-1:0] i_input_coin;
	input [`kNumItems-1:0] i_select_item;
	input i_trigger_return;
		
	output [`kNumItems-1:0] o_available_item;
	output [`kNumItems-1:0] o_output_item;
	output [`kNumCoins-1:0] o_return_coin;


	

	// Do not modify the values.
	wire [31:0] item_price [`kNumItems-1:0];	// Price of each item
	wire [31:0] coin_value [`kNumCoins-1:0];	// Value of each coin
	assign item_price[0] = 400;
	assign item_price[1] = 500;
	assign item_price[2] = 1000;
	assign item_price[3] = 2000;
	assign coin_value[0] = 100;
	assign coin_value[1] = 500;
	assign coin_value[2] = 1000;

	// Internal states. You may add your own net variables.
	reg [`kTotalBits-1:0] current_total, return_total;
	
	// Next internal states. You may add your own net variables.
	reg [`kTotalBits-1:0] current_total_nxt;

	
	// Variables. You may add more your own net variables.
	wire [31:0] wait_time;
	reg [2:0] statea = 3'b000;


	// This module interface, structure, and given a number of modules are not mandatory but recommended.
	// However, Implementations that use modules are mandatory.
	


  	check_time_and_coin check_time_and_coin_module(.i_input_coin(i_input_coin),
									.current_total(current_total),
  									.i_select_item(i_select_item),
									.clk(clk),
									.reset_n(reset_n),
									.wait_time(wait_time),
									.o_return_coin(o_return_coin));

	calculate_current_state calculate_current_state_module(.i_input_coin(i_input_coin),
										.i_select_item(i_select_item),
										.item_price(item_price),
										.coin_value(coin_value),
										.current_total(current_total),
										.current_total_nxt(current_total_nxt),
										.wait_time(wait_time),
										.o_return_coin(o_return_coin),
										.o_available_item(o_available_item),
										.o_output_item(o_output_item),
										.return_total(return_total));
	
  	change_state change_state_module(
						.clk(clk),
						.reset_n(reset_n),
						.current_total_nxt(current_total_nxt),
						.current_total(current_total));


	always @(posedge clk) begin
		if(i_trigger_return && statea == 3'b000) begin
			statea <= 3'b001;
		end else begin
			case(statea)
				3'b001: statea <= 3'b010;
				3'b010: statea <= 3'b011;
				3'b011: 
					if(i_trigger_return) begin
						current_total <= current_total_nxt - return_total;
					end else begin
						statea <= 3'b100;
					end
				default: statea <= 3'b000;
			endcase
		end
	end

endmodule

vending_machine/waveform.vcd
$version Generated by VerilatedVcd $end
$timescale 1ps $end
 $scope module TOP $end
  $var wire 1 5 clk $end
  $var wire 1 6 reset_n $end
  $var wire 3 7 i_input_coin [2:0] $end
  $var wire 4 8 i_select_item [3:0] $end
  $var wire 1 9 i_trigger_return $end
  $var wire 4 : o_available_item [3:0] $end
  $var wire 4 ; o_output_item [3:0] $end
  $var wire 3 < o_return_coin [2:0] $end
  $scope module vending_machine $end
   $var wire 1 5 clk $end
   $var wire 1 6 reset_n $end
   $var wire 3 7 i_input_coin [2:0] $end
   $var wire 4 8 i_select_item [3:0] $end
   $var wire 1 9 i_trigger_return $end
   $var wire 4 : o_available_item [3:0] $end
   $var wire 4 ; o_output_item [3:0] $end
   $var wire 3 < o_return_coin [2:0] $end
   $var wire 32 # item_price[0] [31:0] $end
   $var wire 32 $ item_price[1] [31:0] $end
   $var wire 32 % item_price[2] [31:0] $end
   $var wire 32 & item_price[3] [31:0] $end
   $var wire 32 ' coin_value[0] [31:0] $end
   $var wire 32 ( coin_value[1] [31:0] $end
   $var wire 32 ) coin_value[2] [31:0] $end
   $var wire 32 / current_total [31:0] $end
   $var wire 32 * return_total [31:0] $end
   $var wire 32 + current_total_nxt [31:0] $end
   $var wire 32 0 wait_time [31:0] $end
   $var wire 3 1 statea [2:0] $end
   $scope module calculate_current_state_module $end
    $var wire 3 7 i_input_coin [2:0] $end
    $var wire 3 < o_return_coin [2:0] $end
    $var wire 4 8 i_select_item [3:0] $end
    $var wire 32 # item_price[0] [31:0] $end
    $var wire 32 $ item_price[1] [31:0] $end
    $var wire 32 % item_price[2] [31:0] $end
    $var wire 32 & item_price[3] [31:0] $end
    $var wire 32 ' coin_value[0] [31:0] $end
    $var wire 32 ( coin_value[1] [31:0] $end
    $var wire 32 ) coin_value[2] [31:0] $end
    $var wire 32 / current_total [31:0] $end
    $var wire 32 0 wait_time [31:0] $end
    $var wire 4 : o_available_item [3:0] $end
    $var wire 4 ; o_output_item [3:0] $end
    $var wire 32 + current_total_nxt [31:0] $end
    $var wire 32 * return_total [31:0] $end
    $var wire 32 , input_total [31:0] $end
    $var wire 32 - output_total [31:0] $end
    $var wire 32 2 i [31:0] $end
    $var wire 32 . a [31:0] $end
   $upscope $end
   $scope module change_state_module $end
    $var wire 1 5 clk $end
    $var wire 1 6 reset_n $end
    $var wire 32 + current_total_nxt [31:0] $end
    $var wire 32 / current_total [31:0] $end
   $upscope $end
   $scope module check_time_and_coin_module $end
    $var wire 1 5 clk $end
    $var wire 1 6 reset_n $end
    $var wire 32 / current_total [31:0] $end
    $var wire 3 7 i_input_coin [2:0] $end
    $var wire 4 8 i_select_item [3:0] $end
    $var wire 3 < o_return_coin [2:0] $end
    $var wire 32 0 wait_time [31:0] $end
    $var wire 3 3 prev_i_input_coin [2:0] $end
    $var wire 4 4 prev_i_select_item [3:0] $end
   $upscope $end
  $upscope $end
 $upscope $end
$enddefinitions $end


#0
b00000000000000000000000110010000 #
b00000000000000000000000111110100 $
b00000000000000000000001111101000 %
b00000000000000000000011111010000 &
b00000000000000000000000001100100 '
b00000000000000000000000111110100 (
b00000000000000000000001111101000 )
b00000000000000000000011001000000 *
b11000110010101111110100010101001 +
b00000000000000000000000000000000 ,
b00000000000000000000000000000000 -
b11000110010101111110111011101001 .
b11000110010101111110111011101001 /
b00000000000000000000000000000000 0
b000 1
b00000000000000000000000000000100 2
b100 3
b1011 4
15
16
b000 7
b0000 8
09
b1111 :
b0000 ;
b111 <
#1
05
#2
b00000000000000000000000000000000 *
b00000000000000000000000000000000 +
b00000000000000000000000000000000 .
b00000000000000000000000000000000 /
b000 3
b0000 4
15
06
b0000 :
b000 <
#3
05
#4
15
#5
05
#6
15
16
#7
05
#8
b00000000000000000000000001100100 *
b00000000000000000000000011001000 +
b00000000000000000000000001100100 ,
b00000000000000000000000011001000 .
b00000000000000000000000001100100 /
b00000000000000000000000000001010 0
b001 3
15
b001 7
b001 <
#9
05
#10
b00000000000000000000000001100100 +
b00000000000000000000000000000000 ,
b00000000000000000000000001100100 .
b000 3
15
b000 7
#11
05
#12
b00000000000000000000000100101100 +
b00000000000000000000000001100100 ,
b00000000000000000000000100101100 .
b00000000000000000000000011001000 /
b001 3
15
b001 7
#13
05
#14
b00000000000000000000000011001000 +
b00000000000000000000000000000000 ,
b00000000000000000000000011001000 .
b000 3
15
b000 7
#15
05
#16
b00000000000000000000000110010000 +
b00000000000000000000000001100100 ,
b00000000000000000000000110010000 .
b00000000000000000000000100101100 /
b001 3
15
b001 7
#17
05
#18
b00000000000000000000000100101100 +
b00000000000000000000000000000000 ,
b00000000000000000000000100101100 .
b000 3
15
b000 7
#19
05
#20
b00000000000000000000000111110100 +
b00000000000000000000000001100100 ,
b00000000000000000000000111110100 .
b00000000000000000000000110010000 /
b001 3
15
b001 7
b0001 :
#21
05
#22
b00000000000000000000000110010000 +
b00000000000000000000000000000000 ,
b00000000000000000000000110010000 .
b000 3
15
b000 7
#23
05
#24
b00000000000000000000000111110100 *
b00000000000000000000001001011000 +
b00000000000000000000000001100100 ,
b00000000000000000000001001011000 .
b00000000000000000000000111110100 /
b001 3
15
b001 7
b0011 :
b010 <
#25
05
#26
b00000000000000000000000111110100 +
b00000000000000000000000000000000 ,
b00000000000000000000000111110100 .
b000 3
15
b000 7
#27
05
#28
b00000000000000000000000000001001 0
15
#29
05
#30
b00000000000000000000000000000000 *
b00000000000000000000000000000000 +
b00000000000000000000000000000000 .
b00000000000000000000000000000000 /
b00000000000000000000000000000000 0
15
06
b0000 :
b000 <
#31
05
#32
15
#33
05
#34
15
16
#35
05
#36
b00000000000000000000000111110100 *
b00000000000000000000001111101000 +
b00000000000000000000000111110100 ,
b00000000000000000000001111101000 .
b00000000000000000000000111110100 /
b00000000000000000000000000001010 0
b010 3
15
b010 7
b0011 :
b010 <
#37
05
#38
b00000000000000000000000111110100 +
b00000000000000000000000000000000 ,
b00000000000000000000000111110100 .
b000 3
15
b000 7
#39
05
#40
b00000000000000000000001111101000 *
b00000000000000000000010111011100 +
b00000000000000000000000111110100 ,
b00000000000000000000010111011100 .
b00000000000000000000001111101000 /
b010 3
15
b010 7
b0111 :
b100 <
#41
05
#42
b00000000000000000000001111101000 +
b00000000000000000000000000000000 ,
b00000000000000000000001111101000 .
b000 3
15
b000 7
#43
05
#44
b00000000000000000000010111011100 *
b00000000000000000000011111010000 +
b00000000000000000000000111110100 ,
b00000000000000000000011111010000 .
b00000000000000000000010111011100 /
b010 3
15
b010 7
b110 <
#45
05
#46
b00000000000000000000010111011100 +
b00000000000000000000000000000000 ,
b00000000000000000000010111011100 .
b000 3
15
b000 7
#47
05
#48
b00000000000000000000011001000000 *
b00000000000000000000100111000100 +
b00000000000000000000000111110100 ,
b00000000000000000000100111000100 .
b00000000000000000000011111010000 /
b010 3
15
b010 7
b1111 :
b111 <
#49
05
#50
b00000000000000000000011111010000 +
b00000000000000000000000000000000 ,
b00000000000000000000011111010000 .
b000 3
15
b000 7
#51
05
#52
b00000000000000000000000000001001 0
15
#53
05
#54
b00000000000000000000000000000000 *
b00000000000000000000000000000000 +
b00000000000000000000000000000000 .
b00000000000000000000000000000000 /
b00000000000000000000000000000000 0
15
06
b0000 :
b000 <
#55
05
#56
15
#57
05
#58
15
16
#59
05
#60
b00000000000000000000001111101000 *
b00000000000000000000011111010000 +
b00000000000000000000001111101000 ,
b00000000000000000000011111010000 .
b00000000000000000000001111101000 /
b00000000000000000000000000001010 0
b100 3
15
b100 7
b0111 :
b100 <
#61
05
#62
b00000000000000000000001111101000 +
b00000000000000000000000000000000 ,
b00000000000000000000001111101000 .
b000 3
15
b000 7
#63
05
#64
b00000000000000000000011001000000 *
b00000000000000000000101110111000 +
b00000000000000000000001111101000 ,
b00000000000000000000101110111000 .
b00000000000000000000011111010000 /
b100 3
15
b100 7
b1111 :
b111 <
#65
05
#66
b00000000000000000000011111010000 +
b00000000000000000000000000000000 ,
b00000000000000000000011111010000 .
b000 3
15
b000 7
#67
05
#68
b00000000000000000000000000001001 0
15
#69
05
#70
b00000000000000000000000000000000 *
b00000000000000000000000000000000 +
b00000000000000000000000000000000 .
b00000000000000000000000000000000 /
b00000000000000000000000000000000 0
15
06
b0000 :
b000 <
#71
05
#72
15
#73
05
#74
15
16
#75
05
#76
b00000000000000000000001111101000 *
b00000000000000000000011111010000 +
b00000000000000000000001111101000 ,
b00000000000000000000011111010000 .
b00000000000000000000001111101000 /
b00000000000000000000000000001010 0
b100 3
15
b100 7
b0111 :
b100 <
#77
05
#78
b00000000000000000000001111101000 +
b00000000000000000000000000000000 ,
b00000000000000000000001111101000 .
b000 3
15
b000 7
#79
05
#80
b00000000000000000000011001000000 *
b00000000000000000000101110111000 +
b00000000000000000000001111101000 ,
b00000000000000000000101110111000 .
b00000000000000000000011111010000 /
b100 3
15
b100 7
b1111 :
b111 <
#81
05
#82
b00000000000000000000011111010000 +
b00000000000000000000000000000000 ,
b00000000000000000000011111010000 .
b000 3
15
b000 7
#83
05
#84
b00000000000000000000111110100000 +
b00000000000000000000001111101000 ,
b00000000000000000000111110100000 .
b00000000000000000000101110111000 /
b100 3
15
b100 7
#85
05
#86
b00000000000000000000101110111000 +
b00000000000000000000000000000000 ,
b00000000000000000000101110111000 .
b000 3
15
b000 7
#87
05
#88
b00000000000000000000100010011000 +
b00000000000000000000000110010000 -
b00000000000000000000100010011000 .
b00000000000000000000101000101000 /
b0001 4
15
b0001 8
b0001 ;
#89
05
#90
b00000000000000000000101000101000 +
b00000000000000000000000000000000 -
b00000000000000000000101000101000 .
b0000 4
15
b0000 8
b0000 ;
#91
05
#92
b00000000000000000000000000001001 0
15
#93
05
#94
b00000000000000000000000000001000 0
15
#95
05
#96
b00000000000000000000011100001000 +
b00000000000000000000000110010000 -
b00000000000000000000011100001000 .
b00000000000000000000100010011000 /
b00000000000000000000000000001010 0
b0001 4
15
b0001 8
b0001 ;
#97
05
#98
b00000000000000000000100010011000 +
b00000000000000000000000000000000 -
b00000000000000000000100010011000 .
b0000 4
15
b0000 8
b0000 ;
#99
05
#100
b00000000000000000000000000001001 0
15
#101
05
#102
b00000000000000000000000000001000 0
15
#103
05
#104
b00000000000000000000010101111000 +
b00000000000000000000000110010000 -
b00000000000000000000010101111000 .
b00000000000000000000011100001000 /
b00000000000000000000000000001010 0
b0001 4
15
b0001 8
b0111 :
b0001 ;
#105
05
#106
b00000000000000000000011100001000 +
b00000000000000000000000000000000 -
b00000000000000000000011100001000 .
b0000 4
15
b0000 8
b0000 ;
#107
05
#108
b00000000000000000000000000001001 0
15
#109
05
#110
b00000000000000000000000000001000 0
15
#111
05
#112
b00000000000000000000010001001100 *
b00000000000000000000001111101000 +
b00000000000000000000000110010000 -
b00000000000000000000001111101000 .
b00000000000000000000010101111000 /
b00000000000000000000000000001010 0
b0001 4
15
b0001 8
b0001 ;
b101 <
#113
05
#114
b00000000000000000000010101111000 +
b00000000000000000000000000000000 -
b00000000000000000000010101111000 .
b0000 4
15
b0000 8
b0000 ;
#115
05
#116
b00000000000000000000000000001001 0
15
#117
05
#118
b00000000000000000000000000001000 0
15
#119
05
#120
b00000000000000000000001111101000 *
b00000000000000000000001001011000 +
b00000000000000000000000110010000 -
b00000000000000000000001001011000 .
b00000000000000000000001111101000 /
b00000000000000000000000000001010 0
b0001 4
15
b0001 8
b0001 ;
b100 <
#121
05
#122
b00000000000000000000001111101000 +
b00000000000000000000000000000000 -
b00000000000000000000001111101000 .
b0000 4
15
b0000 8
b0000 ;
#123
05
#124
b00000000000000000000000000001001 0
15
#125
05
#126
b00000000000000000000000000001000 0
15
#127
05
#128
b00000000000000000000001001011000 *
b00000000000000000000000011001000 +
b00000000000000000000000110010000 -
b00000000000000000000000011001000 .
b00000000000000000000001001011000 /
b00000000000000000000000000001010 0
b0001 4
15
b0001 8
b0011 :
b0001 ;
b011 <
#129
05
#130
b00000000000000000000001001011000 +
b00000000000000000000000000000000 -
b00000000000000000000001001011000 .
b0000 4
15
b0000 8
b0000 ;
#131
05
#132
b00000000000000000000000000001001 0
15
#133
05
#134
b00000000000000000000000000001000 0
15
#135
05
#136
b00000000000000000000000001100100 *
b00000000000000000000000011001000 +
b00000000000000000000000011001000 .
b00000000000000000000000011001000 /
b00000000000000000000000000001010 0
b0001 4
15
b0001 8
b0000 :
b001 <
#137
05
#138
b0000 4
15
b0000 8
#139
05
#140
b00000000000000000000000000001001 0
15
#141
05
#142
b00000000000000000000000000001000 0
15
#143
05
#144
b00000000000000000000000000000111 0
15
#145
05
#146
b00000000000000000000000000000110 0
15
#147
05
#148
b00000000000000000000010001001100 *
b00000000000000000000100010011000 +
b00000000000000000000001111101000 ,
b00000000000000000000100010011000 .
b00000000000000000000010010110000 /
b00000000000000000000000000001010 0
b100 3
15
b100 7
b0111 :
b101 <
#149
05
#150
b00000000000000000000010010110000 +
b00000000000000000000000000000000 ,
b00000000000000000000010010110000 .
b000 3
15
b000 7
#151
05
#152
b00000000000000000000011001000000 *
b00000000000000000000110010000000 +
b00000000000000000000001111101000 ,
b00000000000000000000110010000000 .
b00000000000000000000100010011000 /
b100 3
15
b100 7
b1111 :
b111 <
#153
05
#154
b00000000000000000000100010011000 +
b00000000000000000000000000000000 ,
b00000000000000000000100010011000 .
b000 3
15
b000 7
#155
05
#156
b00000000000000000001000001101000 +
b00000000000000000000001111101000 ,
b00000000000000000001000001101000 .
b00000000000000000000110010000000 /
b100 3
15
b100 7
#157
05
#158
b00000000000000000000110010000000 +
b00000000000000000000000000000000 ,
b00000000000000000000110010000000 .
b000 3
15
b000 7
#159
05
#160
b00000000000000000000100010011000 +
b00000000000000000000000111110100 -
b00000000000000000000100010011000 .
b00000000000000000000101010001100 /
b0010 4
15
b0010 8
b0010 ;
#161
05
#162
b00000000000000000000101010001100 +
b00000000000000000000000000000000 -
b00000000000000000000101010001100 .
b0000 4
15
b0000 8
b0000 ;
#163
05
#164
b00000000000000000000000000001001 0
15
#165
05
#166
b00000000000000000000000000001000 0
15
#167
05
#168
b00000000000000000000011010100100 +
b00000000000000000000000111110100 -
b00000000000000000000011010100100 .
b00000000000000000000100010011000 /
b00000000000000000000000000001010 0
b0010 4
15
b0010 8
b0010 ;
#169
05
#170
b00000000000000000000100010011000 +
b00000000000000000000000000000000 -
b00000000000000000000100010011000 .
b0000 4
15
b0000 8
b0000 ;
#171
05
#172
b00000000000000000000000000001001 0
15
#173
05
#174
b00000000000000000000000000001000 0
15
#175
05
#176
b00000000000000000000010010110000 +
b00000000000000000000000111110100 -
b00000000000000000000010010110000 .
b00000000000000000000011010100100 /
b00000000000000000000000000001010 0
b0010 4
15
b0010 8
b0111 :
b0010 ;
#177
05
#178
b00000000000000000000011010100100 +
b00000000000000000000000000000000 -
b00000000000000000000011010100100 .
b0000 4
15
b0000 8
b0000 ;
#179
05
#180
b00000000000000000000000000001001 0
15
#181
05
#182
b00000000000000000000000000001000 0
15
#183
05
#184
b00000000000000000000010001001100 *
b00000000000000000000001010111100 +
b00000000000000000000000111110100 -
b00000000000000000000001010111100 .
b00000000000000000000010010110000 /
b00000000000000000000000000001010 0
b0010 4
15
b0010 8
b0010 ;
b101 <
#185
05
#186
b00000000000000000000010010110000 +
b00000000000000000000000000000000 -
b00000000000000000000010010110000 .
b0000 4
15
b0000 8
b0000 ;
#187
05
#188
b00000000000000000000000000001001 0
15
#189
05
#190
b00000000000000000000000000001000 0
15
#191
05
#192
b00000000000000000000001001011000 *
b00000000000000000000000011001000 +
b00000000000000000000000111110100 -
b00000000000000000000000011001000 .
b00000000000000000000001010111100 /
b00000000000000000000000000001010 0
b0010 4
15
b0010 8
b0011 :
b0010 ;
b011 <
#193
05
#194
b00000000000000000000001010111100 +
b00000000000000000000000000000000 -
b00000000000000000000001010111100 .
b0000 4
15
b0000 8
b0000 ;
#195
05
#196
b00000000000000000000000000001001 0
15
#197
05
#198
b00000000000000000000000000001000 0
15
#199
05
#200
b00000000000000000000000001100100 *
b00000000000000000000000011001000 +
b00000000000000000000000011001000 .
b00000000000000000000000011001000 /
b00000000000000000000000000001010 0
b0010 4
15
b0010 8
b0000 :
b001 <
#201
05
#202
b0000 4
15
b0000 8
#203
05
#204
b00000000000000000000000000001001 0
15
#205
05
#206
b00000000000000000000000000001000 0
15
#207
05
#208
b00000000000000000000000110010000 +
b00000000000000000000000001100100 ,
b00000000000000000000000110010000 .
b00000000000000000000000100101100 /
b00000000000000000000000000001010 0
b001 3
15
b001 7
#209
05
#210
b00000000000000000000000100101100 +
b00000000000000000000000000000000 ,
b00000000000000000000000100101100 .
b000 3
15
b000 7
#211
05
#212
b00000000000000000000000111110100 +
b00000000000000000000000001100100 ,
b00000000000000000000000111110100 .
b00000000000000000000000110010000 /
b001 3
15
b001 7
b0001 :
#213
05
#214
b00000000000000000000000110010000 +
b00000000000000000000000000000000 ,
b00000000000000000000000110010000 .
b000 3
15
b000 7
#215
05
#216
b00000000000000000000010001001100 *
b00000000000000000000100101100000 +
b00000000000000000000001111101000 ,
b00000000000000000000100101100000 .
b00000000000000000000010101111000 /
b100 3
15
b100 7
b0111 :
b101 <
#217
05
#218
b00000000000000000000010101111000 +
b00000000000000000000000000000000 ,
b00000000000000000000010101111000 .
b000 3
15
b000 7
#219
05
#220
b00000000000000000000011001000000 *
b00000000000000000000110101001000 +
b00000000000000000000001111101000 ,
b00000000000000000000110101001000 .
b00000000000000000000100101100000 /
b100 3
15
b100 7
b1111 :
b111 <
#221
05
#222
b00000000000000000000100101100000 +
b00000000000000000000000000000000 ,
b00000000000000000000100101100000 .
b000 3
15
b000 7
#223
05
#224
b00000000000000000001000100110000 +
b00000000000000000000001111101000 ,
b00000000000000000001000100110000 .
b00000000000000000000110101001000 /
b100 3
15
b100 7
#225
05
#226
b00000000000000000000110101001000 +
b00000000000000000000000000000000 ,
b00000000000000000000110101001000 .
b000 3
15
b000 7
#227
05
#228
b00000000000000000000010101111000 +
b00000000000000000000001111101000 -
b00000000000000000000010101111000 .
b00000000000000000000100101100000 /
b0100 4
15
b0100 8
b0100 ;
#229
05
#230
b00000000000000000000100101100000 +
b00000000000000000000000000000000 -
b00000000000000000000100101100000 .
b0000 4
15
b0000 8
b0000 ;
#231
05
#232
b00000000000000000000000000001001 0
15
#233
05
#234
b00000000000000000000000000001000 0
15
#235
05
#236
b00000000000000000000010001001100 *
b00000000000000000000000110010000 +
b00000000000000000000001111101000 -
b00000000000000000000000110010000 .
b00000000000000000000010101111000 /
b00000000000000000000000000001010 0
b0100 4
15
b0100 8
b0111 :
b0100 ;
b101 <
#237
05
#238
b00000000000000000000010101111000 +
b00000000000000000000000000000000 -
b00000000000000000000010101111000 .
b0000 4
15
b0000 8
b0000 ;
#239
05
#240
b00000000000000000000000000001001 0
15
#241
05
#242
b00000000000000000000000000001000 0
15
#243
05
#244
b00000000000000000000000001100100 *
b00000000000000000000000110010000 +
b00000000000000000000000110010000 .
b00000000000000000000000110010000 /
b00000000000000000000000000001010 0
b0100 4
15
b0100 8
b0001 :
b001 <
#245
05
#246
b0000 4
15
b0000 8
#247
05
#248
b00000000000000000000000000001001 0
15
#249
05
#250
b00000000000000000000000000001000 0
15
#251
05
#252
b00000000000000000000010001001100 *
b00000000000000000000100101100000 +
b00000000000000000000001111101000 ,
b00000000000000000000100101100000 .
b00000000000000000000010101111000 /
b00000000000000000000000000001010 0
b100 3
15
b100 7
b0111 :
b101 <
#253
05
#254
b00000000000000000000010101111000 +
b00000000000000000000000000000000 ,
b00000000000000000000010101111000 .
b000 3
15
b000 7
#255
05
#256
b00000000000000000000011001000000 *
b00000000000000000000110101001000 +
b00000000000000000000001111101000 ,
b00000000000000000000110101001000 .
b00000000000000000000100101100000 /
b100 3
15
b100 7
b1111 :
b111 <
#257
05
#258
b00000000000000000000100101100000 +
b00000000000000000000000000000000 ,
b00000000000000000000100101100000 .
b000 3
15
b000 7
#259
05
#260
b00000000000000000001000100110000 +
b00000000000000000000001111101000 ,
b00000000000000000001000100110000 .
b00000000000000000000110101001000 /
b100 3
15
b100 7
#261
05
#262
b00000000000000000000110101001000 +
b00000000000000000000000000000000 ,
b00000000000000000000110101001000 .
b000 3
15
b000 7
#263
05
#264
b00000000000000000000010001001100 *
b00000000000000000000010101111000 +
b00000000000000000000010101111000 .
b00000000000000000000010101111000 /
b1000 4
15
b1000 8
b0111 :
b101 <
#265
05
#266
b0000 4
15
b0000 8
#267
05
#268
b00000000000000000000000000001001 0
15
#269
05
#270
b00000000000000000000000000001000 0
15
#271
05
#272
b00000000000000000000011001000000 *
b00000000000000000000110101001000 +
b00000000000000000000001111101000 ,
b00000000000000000000110101001000 .
b00000000000000000000100101100000 /
b00000000000000000000000000001010 0
b100 3
15
b100 7
b1111 :
b111 <
#273
05
#274
b00000000000000000000100101100000 +
b00000000000000000000000000000000 ,
b00000000000000000000100101100000 .
b000 3
15
b000 7
#275
05
#276
b00000000000000000000000001100100 *
b00000000000000000000000110010000 +
b00000000000000000000000110010000 .
b00000000000000000000000110010000 /
b1000 4
15
b1000 8
b0001 :
b001 <
#277
05
#278
b0000 4
15
b0000 8
#279
05
#280
b00000000000000000000000000001001 0
15
#281
05
#282
b00000000000000000000000000001000 0
15
#283
05
#284
b00000000000000000000000111110100 *
b00000000000000000000001001011000 +
b00000000000000000000000001100100 ,
b00000000000000000000001001011000 .
b00000000000000000000000111110100 /
b00000000000000000000000000001010 0
b001 3
15
b001 7
b0011 :
b010 <
#285
05
#286
b00000000000000000000000111110100 +
b00000000000000000000000000000000 ,
b00000000000000000000000111110100 .
b000 3
15
b000 7
#287
05
#288
b00000000000000000000001001011000 *
b00000000000000000000001010111100 +
b00000000000000000000000001100100 ,
b00000000000000000000001010111100 .
b00000000000000000000001001011000 /
b001 3
15
b001 7
b011 <
#289
05
