vending_machine/vending_machine_def.v
// Title         : vending_machine_def.v
// Author      : Jae-Eon Jo (Jojaeeon@postech.ac.kr) 
//					Dongup Kwon (nankdu7@postech.ac.kr)

// Macro constants (prefix k & CamelCase)
`define kTotalBits 32
  
`define kItemBits 8
`define kNumItems 4

`define kCoinBits 8
`define kNumCoins 3

`define kWaitTime 10

// states 정의
`define s0 2'b00 // 대기 상태
`define s1 2'b01 // 동전 입력 상태
`define s2 2'b10 // 아이템 출력 상태
`define s3 2'b11 // 동전 반환 상태

vending_machine/change_state.v
`include "vending_machine_def.v"


module change_state(clk,reset_n,current_total_nxt,current_total);

	input clk;
	input reset_n;
	input [`kTotalBits-1:0] current_total_nxt;
	output reg [`kTotalBits-1:0] current_total;
	
	// Sequential circuit to reset or update the states
	always @(posedge clk ) begin
		if (!reset_n) begin
			// TODO: reset all states.
			current_total <= 0;
		end
		else begin
			// TODO: update all states.
			current_total <= current_total_nxt;
		end
	end
endmodule

vending_machine/calculate_current_state.v

`include "vending_machine_def.v"
	

module calculate_current_state(i_input_coin,i_select_item,item_price,coin_value,current_total,
current_total_nxt,wait_time,o_return_coin,o_available_item,o_output_item);


	
	input [`kNumCoins-1:0] i_input_coin,o_return_coin;
	input [`kNumItems-1:0]	i_select_item;			
	input [31:0] item_price [`kNumItems-1:0];
	input [31:0] coin_value [`kNumCoins-1:0];	
	input [`kTotalBits-1:0] current_total;
	input [31:0] wait_time;
	output reg [`kNumItems-1:0] o_available_item,o_output_item;
	output reg  [`kTotalBits-1:0] current_total_nxt;
	reg [`kTotalBits-1:0] input_total, output_total, return_total;
	integer i;	



	
	// Combinational logic for the next states
	always @(*) begin
		// TODO: current_total_nxt
		// You don't have to worry about concurrent activations in each input vector (or array).
		// Calculate the next current_total state.
		for (i = 0; i < `kNumCoins; i = i + 1) begin
			input_total = (i_input_coin[i] * coin_value[i][30:0]);
		end
		for (i = 0; i < `kNumCoins; i = i + 1) begin
			return_total =  (o_return_coin[i] * coin_value[i][30:0]);
		end
		current_total_nxt = current_total + input_total - return_total - output_total;
	end

	
	
	// Combinational logic for the outputs
	always @(*) begin
		// TODO: o_available_item
		for (i = 0; i < `kNumCoins; i = i + 1) begin
			if(item_price[i] < current_total) begin
				o_available_item[i] = 1'b1;
			end else begin
				o_available_item[i] = 1'b0;
			end
		end
		// TODO: o_output_item
		if(wait_time > 0) begin
			for (i = 0; i < `kNumCoins; i = i + 1) begin
				if(i_select_item[i] * item_price[i] < current_total) begin
					o_output_item = i_select_item;
					output_total = (i_select_item[i] * item_price[i][30:0]);
				end else begin
					o_output_item = i_select_item;
					output_total = (i_select_item[i] * item_price[i][30:0]);
				end
			end
		end else begin
			o_output_item = 0;
			output_total = 0;
		end
	end
 
	


endmodule

vending_machine/check_time_and_coin.v
`include "vending_machine_def.v"

	

module check_time_and_coin(i_input_coin,i_select_item,clk,reset_n,wait_time,o_return_coin, current_total);
	input clk;
	input reset_n;
	input [`kTotalBits-1:0] current_total;
	input [`kNumCoins-1:0] i_input_coin;
	input [`kNumItems-1:0]	i_select_item;
	output reg  [`kNumCoins-1:0] o_return_coin;
	output reg [31:0] wait_time;

	reg [31:0] a;
	reg[31:0] b;
	// initiate values
	initial begin
		// TODO: initiate values
		wait_time = 0;
		o_return_coin = 0;
		a = 0;
		b = 1;
	end


	// update coin return time
	always @(i_input_coin, i_select_item) begin
		// TODO: update coin return time
		a <= a + 1;
	end

	always @(*) begin
		// TODO: o_return_coin
		if(current_total > 1600) begin
			o_return_coin[2] = 1'b1; 
		end else begin
			o_return_coin[2] = 1'b0;
		end
		if(current_total > 600) begin
			o_return_coin[1] = 1'b1;
		end else begin
			o_return_coin[1] = 1'b0;
		end
		if(current_total > 100) begin
			o_return_coin[0] = 1'b1;
		end else begin
			o_return_coin[0] = 1'b0;
		end
	end

	always @(posedge clk ) begin
		if (!reset_n) begin
		// TODO: reset all states.
		
		wait_time <= 0;
		end
		else begin
		// TODO: update all states.
			if(a == b) begin
				wait_time <= 100;
				b <= b + 1;
			end else begin
				wait_time <= wait_time - 1;
			end
		end
	end
endmodule

vending_machine/vending_machine.v
// Title         : vending_machine.v
// Author      : Jae-Eon Jo (Jojaeeon@postech.ac.kr) 
//			     Dongup Kwon (nankdu7@postech.ac.kr) (2015.03.30)
//			     Jaehun Ryu (jaehunryu@postech.ac.kr) (2021.03.07)

`include "vending_machine_def.v"


module vending_machine (
	clk,							// Clock signal
	reset_n,						// Reset signal (active-low)

	i_input_coin,				// coin is inserted.
	i_select_item,				// item is selected.
	i_trigger_return,			// change-return is triggered 

	o_available_item,			// Sign of the item availability
	o_output_item,			// Sign of the item withdrawal
	o_return_coin				// Sign of the coin return
);

	// Ports Declaration
	// Do not modify the module interface
	input clk;
	input reset_n;
	
	input [`kNumCoins-1:0] i_input_coin;
	input [`kNumItems-1:0] i_select_item;
	input i_trigger_return;
		
	output [`kNumItems-1:0] o_available_item;
	output [`kNumItems-1:0] o_output_item;
	output [`kNumCoins-1:0] o_return_coin;


	

	// Do not modify the values.
	wire [31:0] item_price [`kNumItems-1:0];	// Price of each item
	wire [31:0] coin_value [`kNumCoins-1:0];	// Value of each coin
	assign item_price[0] = 400;
	assign item_price[1] = 500;
	assign item_price[2] = 1000;
	assign item_price[3] = 2000;
	assign coin_value[0] = 100;
	assign coin_value[1] = 500;
	assign coin_value[2] = 1000;

	// Internal states. You may add your own net variables.
	wire [`kTotalBits-1:0] current_total;
	
	// Next internal states. You may add your own net variables.
	wire [`kTotalBits-1:0] current_total_nxt;

	
	// Variables. You may add more your own net variables.
	wire [31:0] wait_time;


	// This module interface, structure, and given a number of modules are not mandatory but recommended.
	// However, Implementations that use modules are mandatory.
		
  	check_time_and_coin check_time_and_coin_module(.i_input_coin(i_input_coin),
									.current_total(current_total),
  									.i_select_item(i_select_item),
									.clk(clk),
									.reset_n(reset_n),
									.wait_time(wait_time),
									.o_return_coin(o_return_coin));

	calculate_current_state calculate_current_state_module(.i_input_coin(i_input_coin),
										.i_select_item(i_select_item),
										.item_price(item_price),
										.coin_value(coin_value),
										.current_total(current_total),
										.current_total_nxt(current_total_nxt),
										.wait_time(wait_time),
										.o_return_coin(o_return_coin),
										.o_available_item(o_available_item),
										.o_output_item(o_output_item));
	
  	change_state change_state_module(
						.clk(clk),
						.reset_n(reset_n),
						.current_total_nxt(current_total_nxt),
						.current_total(current_total));

	always @(*) begin
		
		if(i_trigger_return) begin
			
		end
	end

endmodule

vending_machine/waveform.vcd
$version Generated by VerilatedVcd $end
$timescale 1ps $end
 $scope module TOP $end
  $var wire 1 . clk $end
  $var wire 1 / reset_n $end
  $var wire 3 0 i_input_coin [2:0] $end
  $var wire 4 1 i_select_item [3:0] $end
  $var wire 1 2 i_trigger_return $end
  $var wire 4 3 o_available_item [3:0] $end
  $var wire 4 4 o_output_item [3:0] $end
  $var wire 3 5 o_return_coin [2:0] $end
  $scope module vending_machine $end
   $var wire 1 . clk $end
   $var wire 1 / reset_n $end
   $var wire 3 0 i_input_coin [2:0] $end
   $var wire 4 1 i_select_item [3:0] $end
   $var wire 1 2 i_trigger_return $end
   $var wire 4 3 o_available_item [3:0] $end
   $var wire 4 4 o_output_item [3:0] $end
   $var wire 3 5 o_return_coin [2:0] $end
   $var wire 32 # item_price[0] [31:0] $end
   $var wire 32 $ item_price[1] [31:0] $end
   $var wire 32 % item_price[2] [31:0] $end
   $var wire 32 & item_price[3] [31:0] $end
   $var wire 32 ' coin_value[0] [31:0] $end
   $var wire 32 ( coin_value[1] [31:0] $end
   $var wire 32 ) coin_value[2] [31:0] $end
   $var wire 32 * current_total [31:0] $end
   $var wire 32 6 current_total_nxt [31:0] $end
   $var wire 32 + wait_time [31:0] $end
   $scope module calculate_current_state_module $end
    $var wire 3 0 i_input_coin [2:0] $end
    $var wire 3 5 o_return_coin [2:0] $end
    $var wire 4 1 i_select_item [3:0] $end
    $var wire 32 # item_price[0] [31:0] $end
    $var wire 32 $ item_price[1] [31:0] $end
    $var wire 32 % item_price[2] [31:0] $end
    $var wire 32 & item_price[3] [31:0] $end
    $var wire 32 ' coin_value[0] [31:0] $end
    $var wire 32 ( coin_value[1] [31:0] $end
    $var wire 32 ) coin_value[2] [31:0] $end
    $var wire 32 * current_total [31:0] $end
    $var wire 32 + wait_time [31:0] $end
    $var wire 4 3 o_available_item [3:0] $end
    $var wire 4 4 o_output_item [3:0] $end
    $var wire 32 6 current_total_nxt [31:0] $end
    $var wire 32 7 input_total [31:0] $end
    $var wire 32 8 output_total [31:0] $end
    $var wire 32 9 return_total [31:0] $end
    $var wire 32 , i [31:0] $end
   $upscope $end
   $scope module change_state_module $end
    $var wire 1 . clk $end
    $var wire 1 / reset_n $end
    $var wire 32 6 current_total_nxt [31:0] $end
    $var wire 32 * current_total [31:0] $end
   $upscope $end
   $scope module check_time_and_coin_module $end
    $var wire 1 . clk $end
    $var wire 1 / reset_n $end
    $var wire 32 * current_total [31:0] $end
    $var wire 3 0 i_input_coin [2:0] $end
    $var wire 4 1 i_select_item [3:0] $end
    $var wire 3 5 o_return_coin [2:0] $end
    $var wire 32 + wait_time [31:0] $end
    $var wire 32 : a [31:0] $end
    $var wire 32 - b [31:0] $end
   $upscope $end
  $upscope $end
 $upscope $end
$enddefinitions $end


#0
b00000000000000000000000110010000 #
b00000000000000000000000111110100 $
b00000000000000000000001111101000 %
b00000000000000000000011111010000 &
b00000000000000000000000001100100 '
b00000000000000000000000111110100 (
b00000000000000000000001111101000 )
b11000110010101111110111011101001 *
b00000000000000000000000000000000 +
b00000000000000000000000000000011 ,
b00000000000000000000000000000001 -
1.
1/
b000 0
b0000 1
02
b1111 3
b0000 4
b111 5
b11000110010101111110101100000001 6
b00000000000000000000000000000000 7
b00000000000000000000000000000000 8
b00000000000000000000001111101000 9
b00000000000000000000000000000001 :
#1
0.
#2
b00000000000000000000000000000000 *
1.
0/
b1000 3
b000 5
b00000000000000000000000000000000 6
b00000000000000000000000000000000 9
#3
0.
#4
1.
#5
0.
#6
b00000000000000000000000001100100 +
b00000000000000000000000000000010 -
1.
1/
#7
0.
#8
b00000000000000000000000001100011 +
1.
b001 0
b00000000000000000000000000000010 :
#9
0.
#10
b00000000000000000000000001100100 +
b00000000000000000000000000000011 -
1.
b000 0
b00000000000000000000000000000011 :
#11
0.
#12
b00000000000000000000000000000100 -
1.
b001 0
b00000000000000000000000000000100 :
#13
0.
#14
b00000000000000000000000000000101 -
1.
b000 0
b00000000000000000000000000000101 :
#15
0.
#16
b00000000000000000000000000000110 -
1.
b001 0
b00000000000000000000000000000110 :
#17
0.
#18
b00000000000000000000000000000111 -
1.
b000 0
b00000000000000000000000000000111 :
#19
0.
#20
b00000000000000000000000000001000 -
1.
b001 0
b00000000000000000000000000001000 :
#21
0.
#22
b00000000000000000000000000001001 -
1.
b000 0
b00000000000000000000000000001001 :
#23
0.
#24
b00000000000000000000000000001010 -
1.
b001 0
b00000000000000000000000000001010 :
#25
0.
#26
b00000000000000000000000000001011 -
1.
b000 0
b00000000000000000000000000001011 :
#27
0.
#28
b00000000000000000000000000001100 -
1.
#29
0.
#30
b00000000000000000000000000000000 +
1.
0/
#31
0.
#32
1.
#33
0.
#34
b11111111111111111111111111111111 +
1.
1/
#35
0.
#36
b11111111111111111111111111111110 +
1.
b010 0
b00000000000000000000000000001100 :
#37
0.
#38
b00000000000000000000000001100100 +
b00000000000000000000000000001101 -
1.
b000 0
b00000000000000000000000000001101 :
#39
0.
#40
b00000000000000000000000000001110 -
1.
b010 0
b00000000000000000000000000001110 :
#41
0.
#42
b00000000000000000000000000001111 -
1.
b000 0
b00000000000000000000000000001111 :
#43
0.
#44
b00000000000000000000000000010000 -
1.
b010 0
b00000000000000000000000000010000 :
#45
0.
#46
b00000000000000000000000000010001 -
1.
b000 0
b00000000000000000000000000010001 :
#47
0.
#48
b00000000000000000000000000010010 -
1.
b010 0
b00000000000000000000000000010010 :
#49
0.
#50
b00000000000000000000000000010011 -
1.
b000 0
b00000000000000000000000000010011 :
#51
0.
#52
b00000000000000000000000000010100 -
1.
#53
0.
#54
b00000000000000000000000000000000 +
1.
0/
#55
0.
#56
1.
#57
0.
#58
b11111111111111111111111111111111 +
1.
1/
#59
0.
#60
b00000000000000000000001111101000 *
b11111111111111111111111111111110 +
1.
b100 0
b1011 3
b011 5
b00000000000000000000011111010000 6
b00000000000000000000001111101000 7
b00000000000000000000000000010100 :
#61
0.
#62
b00000000000000000000000001100100 +
b00000000000000000000000000010101 -
1.
b000 0
b00000000000000000000001111101000 6
b00000000000000000000000000000000 7
b00000000000000000000000000010101 :
#63
0.
#64
b00000000000000000000011111010000 *
b00000000000000000000000000010110 -
1.
b100 0
b1111 3
b111 5
b00000000000000000000011111010000 6
b00000000000000000000001111101000 7
b00000000000000000000001111101000 9
b00000000000000000000000000010110 :
#65
0.
#66
b00000000000000000000001111101000 *
b00000000000000000000000000010111 -
1.
b000 0
b1011 3
b011 5
b00000000000000000000001111101000 6
b00000000000000000000000000000000 7
b00000000000000000000000000000000 9
b00000000000000000000000000010111 :
#67
0.
#68
b00000000000000000000000000011000 -
1.
#69
0.
#70
b00000000000000000000000000000000 *
b00000000000000000000000000000000 +
1.
0/
b1000 3
b000 5
b00000000000000000000000000000000 6
#71
0.
#72
1.
#73
0.
#74
b11111111111111111111111111111111 +
1.
1/
#75
0.
#76
b00000000000000000000001111101000 *
b11111111111111111111111111111110 +
1.
b100 0
b1011 3
b011 5
b00000000000000000000011111010000 6
b00000000000000000000001111101000 7
b00000000000000000000000000011000 :
#77
0.
#78
b00000000000000000000000001100100 +
b00000000000000000000000000011001 -
1.
b000 0
b00000000000000000000001111101000 6
b00000000000000000000000000000000 7
b00000000000000000000000000011001 :
#79
0.
#80
b00000000000000000000011111010000 *
b00000000000000000000000000011010 -
1.
b100 0
b1111 3
b111 5
b00000000000000000000011111010000 6
b00000000000000000000001111101000 7
b00000000000000000000001111101000 9
b00000000000000000000000000011010 :
#81
0.
#82
b00000000000000000000001111101000 *
b00000000000000000000000000011011 -
1.
b000 0
b1011 3
b011 5
b00000000000000000000001111101000 6
b00000000000000000000000000000000 7
b00000000000000000000000000000000 9
b00000000000000000000000000011011 :
#83
0.
#84
b00000000000000000000011111010000 *
b00000000000000000000000000011100 -
1.
b100 0
b1111 3
b111 5
b00000000000000000000011111010000 6
b00000000000000000000001111101000 7
b00000000000000000000001111101000 9
b00000000000000000000000000011100 :
#85
0.
#86
b00000000000000000000001111101000 *
b00000000000000000000000000011101 -
1.
b000 0
b1011 3
b011 5
b00000000000000000000001111101000 6
b00000000000000000000000000000000 7
b00000000000000000000000000000000 9
b00000000000000000000000000011101 :
#87
0.
#88
b00000000000000000000000000011110 -
1.
b0001 1
b0001 4
b00000000000000000000000000011110 :
#89
0.
#90
b00000000000000000000000000011111 -
1.
b0000 1
b0000 4
b00000000000000000000000000011111 :
#91
0.
#92
b00000000000000000000000000100000 -
1.
#93
0.
#94
b00000000000000000000000001100011 +
1.
#95
0.
#96
b00000000000000000000000001100010 +
1.
b0001 1
b0001 4
b00000000000000000000000000100000 :
#97
0.
#98
b00000000000000000000000001100100 +
b00000000000000000000000000100001 -
1.
b0000 1
b0000 4
b00000000000000000000000000100001 :
#99
0.
#100
b00000000000000000000000000100010 -
1.
#101
0.
#102
b00000000000000000000000001100011 +
1.
#103
0.
#104
b00000000000000000000000001100010 +
1.
b0001 1
b0001 4
b00000000000000000000000000100010 :
#105
0.
#106
b00000000000000000000000001100100 +
b00000000000000000000000000100011 -
1.
b0000 1
b0000 4
b00000000000000000000000000100011 :
#107
0.
#108
b00000000000000000000000000100100 -
1.
#109
0.
#110
b00000000000000000000000001100011 +
1.
#111
0.
#112
b00000000000000000000000001100010 +
1.
b0001 1
b0001 4
b00000000000000000000000000100100 :
#113
0.
#114
b00000000000000000000000001100100 +
b00000000000000000000000000100101 -
1.
b0000 1
b0000 4
b00000000000000000000000000100101 :
#115
0.
#116
b00000000000000000000000000100110 -
1.
#117
0.
#118
b00000000000000000000000001100011 +
1.
#119
0.
#120
b00000000000000000000000001100010 +
1.
b0001 1
b0001 4
b00000000000000000000000000100110 :
#121
0.
#122
b00000000000000000000000001100100 +
b00000000000000000000000000100111 -
1.
b0000 1
b0000 4
b00000000000000000000000000100111 :
#123
0.
#124
b00000000000000000000000000101000 -
1.
#125
0.
#126
b00000000000000000000000001100011 +
1.
#127
0.
#128
b00000000000000000000000001100010 +
1.
b0001 1
b0001 4
b00000000000000000000000000101000 :
#129
0.
#130
b00000000000000000000000001100100 +
b00000000000000000000000000101001 -
1.
b0000 1
b0000 4
b00000000000000000000000000101001 :
#131
0.
#132
b00000000000000000000000000101010 -
1.
#133
0.
#134
b00000000000000000000000001100011 +
1.
#135
0.
#136
b00000000000000000000000001100010 +
1.
b0001 1
b0001 4
b00000000000000000000000000101010 :
#137
0.
#138
b00000000000000000000000001100100 +
b00000000000000000000000000101011 -
1.
b0000 1
b0000 4
b00000000000000000000000000101011 :
#139
0.
#140
b00000000000000000000000000101100 -
1.
#141
0.
#142
b00000000000000000000000001100011 +
1.
#143
0.
#144
b00000000000000000000000001100010 +
1.
#145
0.
#146
b00000000000000000000000001100001 +
1.
#147
0.
#148
b00000000000000000000011111010000 *
b00000000000000000000000001100000 +
1.
b100 0
b1111 3
b111 5
b00000000000000000000011111010000 6
b00000000000000000000001111101000 7
b00000000000000000000001111101000 9
b00000000000000000000000000101100 :
#149
0.
#150
b00000000000000000000001111101000 *
b00000000000000000000000001100100 +
b00000000000000000000000000101101 -
1.
b000 0
b1011 3
b011 5
b00000000000000000000001111101000 6
b00000000000000000000000000000000 7
b00000000000000000000000000000000 9
b00000000000000000000000000101101 :
#151
0.
#152
b00000000000000000000011111010000 *
b00000000000000000000000000101110 -
1.
b100 0
b1111 3
b111 5
b00000000000000000000011111010000 6
b00000000000000000000001111101000 7
b00000000000000000000001111101000 9
b00000000000000000000000000101110 :
#153
0.
#154
b00000000000000000000001111101000 *
b00000000000000000000000000101111 -
1.
b000 0
b1011 3
b011 5
b00000000000000000000001111101000 6
b00000000000000000000000000000000 7
b00000000000000000000000000000000 9
b00000000000000000000000000101111 :
#155
0.
#156
b00000000000000000000011111010000 *
b00000000000000000000000000110000 -
1.
b100 0
b1111 3
b111 5
b00000000000000000000011111010000 6
b00000000000000000000001111101000 7
b00000000000000000000001111101000 9
b00000000000000000000000000110000 :
#157
0.
#158
b00000000000000000000001111101000 *
b00000000000000000000000000110001 -
1.
b000 0
b1011 3
b011 5
b00000000000000000000001111101000 6
b00000000000000000000000000000000 7
b00000000000000000000000000000000 9
b00000000000000000000000000110001 :
#159
0.
#160
b00000000000000000000000000110010 -
1.
b0010 1
b0010 4
b00000000000000000000000000110010 :
#161
0.
#162
b00000000000000000000000000110011 -
1.
b0000 1
b0000 4
b00000000000000000000000000110011 :
#163
0.
#164
b00000000000000000000000000110100 -
1.
#165
0.
#166
b00000000000000000000000001100011 +
1.
#167
0.
#168
b00000000000000000000000001100010 +
1.
b0010 1
b0010 4
b00000000000000000000000000110100 :
#169
0.
#170
b00000000000000000000000001100100 +
b00000000000000000000000000110101 -
1.
b0000 1
b0000 4
b00000000000000000000000000110101 :
#171
0.
#172
b00000000000000000000000000110110 -
1.
#173
0.
#174
b00000000000000000000000001100011 +
1.
#175
0.
#176
b00000000000000000000000001100010 +
1.
b0010 1
b0010 4
b00000000000000000000000000110110 :
#177
0.
#178
b00000000000000000000000001100100 +
b00000000000000000000000000110111 -
1.
b0000 1
b0000 4
b00000000000000000000000000110111 :
#179
0.
#180
b00000000000000000000000000111000 -
1.
#181
0.
#182
b00000000000000000000000001100011 +
1.
#183
0.
#184
b00000000000000000000000001100010 +
1.
b0010 1
b0010 4
b00000000000000000000000000111000 :
#185
0.
#186
b00000000000000000000000001100100 +
b00000000000000000000000000111001 -
1.
b0000 1
b0000 4
b00000000000000000000000000111001 :
#187
0.
#188
b00000000000000000000000000111010 -
1.
#189
0.
#190
b00000000000000000000000001100011 +
1.
#191
0.
#192
b00000000000000000000000001100010 +
1.
b0010 1
b0010 4
b00000000000000000000000000111010 :
#193
0.
#194
b00000000000000000000000001100100 +
b00000000000000000000000000111011 -
1.
b0000 1
b0000 4
b00000000000000000000000000111011 :
#195
0.
#196
b00000000000000000000000000111100 -
1.
#197
0.
#198
b00000000000000000000000001100011 +
1.
#199
0.
#200
b00000000000000000000000001100010 +
1.
b0010 1
b0010 4
b00000000000000000000000000111100 :
#201
0.
#202
b00000000000000000000000001100100 +
b00000000000000000000000000111101 -
1.
b0000 1
b0000 4
b00000000000000000000000000111101 :
#203
0.
#204
b00000000000000000000000000111110 -
1.
#205
0.
#206
b00000000000000000000000001100011 +
1.
#207
0.
#208
b00000000000000000000000001100010 +
1.
b001 0
b00000000000000000000000000111110 :
#209
0.
#210
b00000000000000000000000001100100 +
b00000000000000000000000000111111 -
1.
b000 0
b00000000000000000000000000111111 :
#211
0.
#212
b00000000000000000000000001000000 -
1.
b001 0
b00000000000000000000000001000000 :
#213
0.
#214
b00000000000000000000000001000001 -
1.
b000 0
b00000000000000000000000001000001 :
#215
0.
#216
b00000000000000000000011111010000 *
b00000000000000000000000001000010 -
1.
b100 0
b1111 3
b111 5
b00000000000000000000011111010000 6
b00000000000000000000001111101000 7
b00000000000000000000001111101000 9
b00000000000000000000000001000010 :
#217
0.
#218
b00000000000000000000001111101000 *
b00000000000000000000000001000011 -
1.
b000 0
b1011 3
b011 5
b00000000000000000000001111101000 6
b00000000000000000000000000000000 7
b00000000000000000000000000000000 9
b00000000000000000000000001000011 :
#219
0.
#220
b00000000000000000000011111010000 *
b00000000000000000000000001000100 -
1.
b100 0
b1111 3
b111 5
b00000000000000000000011111010000 6
b00000000000000000000001111101000 7
b00000000000000000000001111101000 9
b00000000000000000000000001000100 :
#221
0.
#222
b00000000000000000000001111101000 *
b00000000000000000000000001000101 -
1.
b000 0
b1011 3
b011 5
b00000000000000000000001111101000 6
b00000000000000000000000000000000 7
b00000000000000000000000000000000 9
b00000000000000000000000001000101 :
#223
0.
#224
b00000000000000000000011111010000 *
b00000000000000000000000001000110 -
1.
b100 0
b1111 3
b111 5
b00000000000000000000011111010000 6
b00000000000000000000001111101000 7
b00000000000000000000001111101000 9
b00000000000000000000000001000110 :
#225
0.
#226
b00000000000000000000001111101000 *
b00000000000000000000000001000111 -
1.
b000 0
b1011 3
b011 5
b00000000000000000000001111101000 6
b00000000000000000000000000000000 7
b00000000000000000000000000000000 9
b00000000000000000000000001000111 :
#227
0.
#228
b00000000000000000000000000000000 *
b00000000000000000000000001001000 -
1.
b0100 1
b1000 3
b0100 4
b000 5
b11111111111111111111110000011000 6
b00000000000000000000001111101000 8
b00000000000000000000000001001000 :
#229
0.
#230
b00000000000000000000000001001001 -
1.
b0000 1
b0000 4
b00000000000000000000000000000000 6
b00000000000000000000000000000000 8
b00000000000000000000000001001001 :
#231
0.
#232
b00000000000000000000000001001010 -
1.
#233
0.
#234
b00000000000000000000000001100011 +
1.
#235
0.
#236
b11111111111111111111110000011000 *
b00000000000000000000000001100010 +
1.
b0100 1
b1111 3
b0100 4
b111 5
b11111111111111111111010001001000 6
b00000000000000000000001111101000 8
b00000000000000000000001111101000 9
b00000000000000000000000001001010 :
#237
0.
#238
b11111111111111111111100000110000 *
b00000000000000000000000001100100 +
b00000000000000000000000001001011 -
1.
b0000 1
b0000 4
b00000000000000000000000000000000 8
b00000000000000000000000001001011 :
#239
0.
#240
b11111111111111111111010001001000 *
b00000000000000000000000001001100 -
1.
b11111111111111111111000001100000 6
#241
0.
#242
b11111111111111111111000001100000 *
b00000000000000000000000001100011 +
1.
b11111111111111111110110001111000 6
#243
0.
#244
b11111111111111111110100010010000 *
b00000000000000000000000001100010 +
1.
b0100 1
b0100 4
b11111111111111111110000011000000 6
b00000000000000000000001111101000 8
b00000000000000000000000001001100 :
#245
0.
#246
b11111111111111111110010010101000 *
b00000000000000000000000001100100 +
b00000000000000000000000001001101 -
1.
b0000 1
b0000 4
b00000000000000000000000000000000 8
b00000000000000000000000001001101 :
#247
0.
#248
b11111111111111111110000011000000 *
b00000000000000000000000001001110 -
1.
b11111111111111111101110011011000 6
#249
0.
#250
b11111111111111111101110011011000 *
b00000000000000000000000001100011 +
1.
b11111111111111111101100011110000 6
#251
0.
#252
b00000000000000000000000001100010 +
1.
b100 0
b11111111111111111101110011011000 6
b00000000000000000000001111101000 7
b00000000000000000000000001001110 :
#253
0.
#254
b11111111111111111101100011110000 *
b00000000000000000000000001100100 +
b00000000000000000000000001001111 -
1.
b000 0
b11111111111111111101010100001000 6
b00000000000000000000000000000000 7
b00000000000000000000000001001111 :
#255
0.
#256
b00000000000000000000000001010000 -
1.
b100 0
b11111111111111111101100011110000 6
b00000000000000000000001111101000 7
b00000000000000000000000001010000 :
#257
0.
#258
b11111111111111111101010100001000 *
b00000000000000000000000001010001 -
1.
b000 0
b11111111111111111101000100100000 6
b00000000000000000000000000000000 7
b00000000000000000000000001010001 :
#259
0.
#260
b00000000000000000000000001010010 -
1.
b100 0
b11111111111111111101010100001000 6
b00000000000000000000001111101000 7
b00000000000000000000000001010010 :
#261
0.
#262
b11111111111111111101000100100000 *
b00000000000000000000000001010011 -
1.
b000 0
b11111111111111111100110100111000 6
b00000000000000000000000000000000 7
b00000000000000000000000001010011 :
#263
0.
#264
b11111111111111111100110100111000 *
b00000000000000000000000001010100 -
1.
b1000 1
b1000 4
b11111111111111111100100101010000 6
b00000000000000000000000001010100 :
#265
0.
#266
b11111111111111111100100101010000 *
b00000000000000000000000001010101 -
1.
b0000 1
b0000 4
b11111111111111111100010101101000 6
b00000000000000000000000001010101 :
#267
0.
#268
b11111111111111111100010101101000 *
b00000000000000000000000001010110 -
1.
b11111111111111111100000110000000 6
#269
0.
#270
b11111111111111111100000110000000 *
b00000000000000000000000001100011 +
1.
b11111111111111111011110110011000 6
#271
0.
#272
b00000000000000000000000001100010 +
1.
b100 0
b11111111111111111100000110000000 6
b00000000000000000000001111101000 7
b00000000000000000000000001010110 :
#273
0.
#274
b11111111111111111011110110011000 *
b00000000000000000000000001100100 +
b00000000000000000000000001010111 -
1.
b000 0
b11111111111111111011100110110000 6
b00000000000000000000000000000000 7
b00000000000000000000000001010111 :
#275
0.
#276
b11111111111111111011100110110000 *
b00000000000000000000000001011000 -
1.
b1000 1
b1000 4
b11111111111111111011010111001000 6
b00000000000000000000000001011000 :
#277
0.
#278
b11111111111111111011010111001000 *
b00000000000000000000000001011001 -
1.
b0000 1
b0000 4
b11111111111111111011000111100000 6
b00000000000000000000000001011001 :
#279
0.
#280
b11111111111111111011000111100000 *
b00000000000000000000000001011010 -
1.
b11111111111111111010110111111000 6
#281
0.
#282
b11111111111111111010110111111000 *
b00000000000000000000000001100011 +
1.
b11111111111111111010101000010000 6
#283
0.
#284
b11111111111111111010101000010000 *
b00000000000000000000000001100010 +
1.
b001 0
b11111111111111111010011000101000 6
b00000000000000000000000001011010 :
#285
0.
#286
b11111111111111111010011000101000 *
b00000000000000000000000001100100 +
b00000000000000000000000001011011 -
1.
b000 0
b11111111111111111010001001000000 6
b00000000000000000000000001011011 :
#287
0.
#288
b11111111111111111010001001000000 *
b00000000000000000000000001011100 -
1.
b001 0
b11111111111111111001111001011000 6
b00000000000000000000000001011100 :
#289
0.
#290
b11111111111111111001111001011000 *
b00000000000000000000000001011101 -
1.
b000 0
b11111111111111111001101001110000 6
b00000000000000000000000001011101 :
#291
0.
#292
b11111111111111111001101001110000 *
b00000000000000000000000001011110 -
1.
b001 0
b11111111111111111001011010001000 6
b00000000000000000000000001011110 :
#293
0.
#294
b11111111111111111001011010001000 *
b00000000000000000000000001011111 -
1.
b000 0
b11111111111111111001001010100000 6
b00000000000000000000000001011111 :
#295
0.
#296
b11111111111111111001001010100000 *
b00000000000000000000000001100000 -
1.
b001 0
b11111111111111111000111010111000 6
b00000000000000000000000001100000 :
#297
0.
#298
b11111111111111111000111010111000 *
b00000000000000000000000001100001 -
1.
b000 0
b11111111111111111000101011010000 6
b00000000000000000000000001100001 :
#299
0.
#300
b11111111111111111000101011010000 *
b00000000000000000000000001100010 -
1.
b010 0
b11111111111111111000011011101000 6
b00000000000000000000000001100010 :
#301
0.
#302
b11111111111111111000011011101000 *
b00000000000000000000000001100011 -
1.
b000 0
b11111111111111111000001100000000 6
b00000000000000000000000001100011 :
#303
0.
#304
b11111111111111111000001100000000 *
b00000000000000000000000001100100 -
1.
b010 0
b11111111111111110111111100011000 6
b00000000000000000000000001100100 :
#305
0.
#306
b11111111111111110111111100011000 *
b00000000000000000000000001100101 -
1.
b000 0
b11111111111111110111101100110000 6
b00000000000000000000000001100101 :
#307
0.
#308
b00000000000000000000000001100110 -
1.
b100 0
b11111111111111110111111100011000 6
b00000000000000000000001111101000 7
b00000000000000000000000001100110 :
#309
0.
#310
b11111111111111110111101100110000 *
b00000000000000000000000001100111 -
1.
b000 0
b11111111111111110111011101001000 6
b00000000000000000000000000000000 7
b00000000000000000000000001100111 :
#311
0.
#312
b11111111111111110111011101001000 *
b00000000000000000000000001101000 -
1.
b11111111111111110111001101100000 6
#313
0.
#314
b11111111111111110111001101100000 *
b00000000000000000000000001100011 +
1.
b11111111111111110110111101111000 6
#315
0.
#316
b11111111111111110110111101111000 *
b00000000000000000000000001100010 +
1.
b11111111111111110110101110010000 6
#317
0.
#318
b11111111111111110110101110010000 *
b00000000000000000000000001100001 +
1.
b11111111111111110110011110101000 6
#319
0.
#320
b11111111111111110110011110101000 *
b00000000000000000000000001100000 +
1.
b11111111111111110110001111000000 6
#321
0.
#322
b11111111111111110110001111000000 *
b00000000000000000000000001011111 +
1.
b11111111111111110101111111011000 6
#323
0.
